tiny.sv


module alu16 #(parameter WIDTH = 16) (clk, reset, A, B, E, L, LS, Cn, PI, PS, psr);
    input [WIDTH - 1:0] A, B;
    input [3:0] L;
    input Cn;
    input clk;
    input reset;
	input LS;
    input PI, PS;

    output [WIDTH - 1:0] E;
    output reg [3:0] psr;

    wire [WIDTH - 1:0] lA;
    wire [WIDTH - 1:0] lB;
    wire [WIDTH:0] tE;

	genvar i;

	for (i = 0; i < WIDTH; i = i + 1)
		assign lB[i] = A[i] ? (B[i] ? L[3] : L[2]) : (B[i] ? L[1] : L[0]);

	assign lA = LS ? 0: A;
    assign tE = { 1'b0, lA } + { 1'b0, lB } + (1 & Cn);
    assign E = tE[WIDTH - 1:0];

    always @(posedge clk or posedge reset) begin
        if (reset == 1) begin
            psr <= 0;
        end
        else
        if (PI == 1) begin
            if (PS == 1) begin
                psr <= tE[3:0];
            end
            else begin
                psr <= {
					tE[16],
					tE[WIDTH - 1],
					tE,
					(E[WIDTH - 1] & ~A[WIDTH - 1] & ~lB[WIDTH - 1]) | (~E[WIDTH - 1] & A[WIDTH - 1] & lB[WIDTH - 1])
				};
            end	
        end
    end
endmodule


module memory #(parameter WIDTH = 16) (clk, reset, MI, RI, write, read, mar);
    input clk, MI, RI;
    input reset;
    
    output [WIDTH - 1:0] mar;
    input [WIDTH - 1:0] write;
    output [WIDTH - 1:0] read;
    
    reg [WIDTH - 1:0] mem_addr_reg;
    reg [WIDTH - 1:0] ram [2**16-1:0];
    
    integer i;

    assign mar = mem_addr_reg;
	
	// assign TYPE_IMM = ~inst[7] & ~inst[6];	// 0
	// assign TYPE_ABS = ~inst[7] & inst[6];	// 1
	// assign TYPE_OFF = inst[7] & ~inst[6];	// 2
	// assign TYPE_REG = inst[7] & inst[6];	// 3
	
	parameter imm = 0 << 6;
	parameter abs = 1 << 6;
	parameter off = 2 << 6;

	parameter loadi	= 	5'b00001;
	parameter loada =	loadi | abs;

	parameter store = 	5'b00010 | abs;

	parameter jump 	= 	5'b00100;
	parameter jumpz =	5'b00101;
	parameter jumpc =	5'b00110;
	parameter jumpn =	5'b00111;

	parameter add 	= 	5'b01000;
	parameter adc 	= 	5'b01001;
	parameter sbb 	= 	5'b01010;
	parameter sub 	= 	5'b01011;
	
	parameter adda 	= 	add | abs;
	parameter adca 	= 	adc | abs;
	parameter sbba 	= 	sbb | abs;
	parameter suba 	= 	sub | abs;
		
	parameter tmp = 10;
	parameter first = 11;
	parameter second = 12;
	parameter count = 13;

	integer org;
	
	integer start, finish;

    always @(posedge clk or posedge reset) begin
        if (reset == 1) begin
            mem_addr_reg <= 0;

            for (i = 0; i < 2**(WIDTH - 1); i++)
                ram[i] = 0;
			
			org = 100;

			ram[0] = org - 1;

			ram[first] = 0;
			ram[second] = 1;
			ram[count] = 10;

			start = org++;
			ram[start] = loada;
			ram[org++] = count;
			ram[org++] = sub;
			ram[org++] = 10;

			finish = org++;
			ram[finish] = 8'hff;
			ram[org++] = 4;
        end
        else
        begin
            if (MI == 1)
                mem_addr_reg <= write;

            if (RI == 1)
                ram[mem_addr_reg] <= write;
        end
    end

    assign read = ram[mem_addr_reg];
endmodule


module sync_mux_2x1 #(parameter WIDTH = 16) (clk, reset, sel, enable, in0, in1, out);
    input sel, enable, clk, reset;
    input [WIDTH - 1:0] in0, in1;

    output reg [WIDTH - 1:0] out;

    always @(posedge clk or posedge reset) begin
        if (reset == 1)
            out = 0;
        else
        if (enable) begin
            if (sel == 1)
                out = in1;
            else
                out = in0;
        end
    end
endmodule

module controlunit(clk, reset, inst, cAI, cAS, cPI, cPS, cMI, cRI, cES, cCn, cL, cLS, cII, decode, counter);
	// Enable Control Lines

    parameter AI = 1 << 0;
    parameter AS = 1 << 1;
    parameter PI = 1 << 2;
    parameter PS = 1 << 3;
    parameter MI = 1 << 4;
    parameter RI = 1 << 5;
    parameter ES = 1 << 6;
    parameter Cn = 1 << 7;
    parameter LS = 1 << 8;
    parameter II = 1 << 9;

	// ALU Control Liines

    parameter GEN_0 = 14'b0000_0000000000 | LS;
    parameter GEN_1 = 14'b1111_0000000000 | LS;
    parameter BUF_A = 14'b1100_0000000000;
    parameter NEG_A = 14'b0011_0000000000;
    parameter BUF_B = 14'b1010_0000000000;
    parameter NEG_B = 14'b0101_0000000000;

    // parameter NAND = 14'b0111_0000000000 | LS;
    // parameter AND = 14'b1000_0000000000 | LS;
    // parameter OR = 14'b1110_0000000000 | LS;
    // parameter NOR = 14'b0001_0000000000 | LS;
    // parameter XOR = 14'b0110_0000000000 | LS;
    // parameter XNOR = 14'b1001_0000000000 | LS;

	// parameter INC_A = BUF_A | Cn | LS;
	// parameter DEC_A = NEG_A | LS;

	// parameter INC_B = BUF_B | Cn | LS;
	// parameter DEC_B = NEG_B | LS;

    // parameter ADD = BUF_B;
	// parameter ADC = BUF_B | Cn;
	// parameter SUB = NEG_B | Cn;
	// parameter SBB = NEG_B;
	
	// parameter INST_IMM = 1;
	// parameter INST_ABS = 2;
	// parameter INST_OFF = 3;
	
	// // Instructions
	// parameter NOP = 8'b0;
	
	// parameter INST_TYPE_REG = 0;
	// parameter INST_TYPE_IMM = 1;
	// parameter INST_TYPE_ABS = 2;
	// parameter INST_TYPE_OFF = 3;

	// ALU INT - ADDRESSING_TYPE[2] - INST_TYPE[]

	parameter load 	= 	6'b000001;
	parameter loadi 	= 	6'b000001;

	parameter store = 	6'b000010;

	parameter jump 	= 	6'b000100;
	parameter jumpz =	6'b000101;
	parameter jumpc =	6'b000110;
	parameter jumpn =	6'b000111;

	parameter add 	= 	6'b001000;
	parameter addc 	= 	6'b001001;
	parameter subb 	= 	6'b001010;
	parameter sub 	= 	6'b001011;

	input clk;
    input reset;
    input [7:0] inst;

    output wire cAI, cAS;
    output wire cPI, cPS;
    output wire cMI, cRI;
    output wire cES;
    output wire cCn;
    output wire cLS;
    output wire cII;
    output wire [3:0] cL;

    output [15:0] decode;
    output reg [2:0] counter;

	wire TYPE_REG, TYPE_IMM, TYPE_ABS, TYPE_OFF;
	wire [5:0] opcode;

	reg reset_counter;

	assign TYPE_IMM = ~inst[7] & ~inst[6];	// 0
	assign TYPE_ABS = ~inst[7] & inst[6];	// 1
	assign TYPE_OFF = inst[7] & ~inst[6];	// 2
	assign TYPE_REG = inst[7] & inst[6];	// 3

	assign opcode = inst[5:0];

    always @(negedge clk or posedge reset) begin
        if (reset == 1) begin
            counter <= 0;
        end else begin
			// case (counter)
			// 	4'h0:
			// 		decode <= GEN_0 | MI;

			// 	4'h1:
			// 		decode <= BUF_B | Cn | MI | RI | LS;

			// 	4'h2:
			// 		decode <= II | GEN_0 | MI;

			// 	4'h3:
			// 		decode <= BUF_B | Cn | MI | RI | LS;

			// 	4'h4:
			// 		decode <=
			// 			TYPE_IMM ? 
			// 				(opcode == load) ? AI : ((opcode == add) ? BUF_B | AS | AI : 0)
			// 				// (opcode == add) ? 
			// 			: 0;
			// endcase

			// if (counter == 5)
			// 	counter <= 0;
			// else

			counter <= counter + 1;
        end
    end
	
	assign decode =
		counter == 0 ? GEN_0 | MI:
		counter == 1 ? BUF_B | Cn | MI | RI | LS:
		counter == 2 ? II | GEN_0 | MI:
		counter == 3 ? BUF_B | Cn | MI | RI | LS:
		counter == 4 ?
			TYPE_IMM ?
				opcode == load ? AI:
				opcode == add ? BUF_B | PI | AS | AI | AS:
				opcode == addc ? BUF_B | PI | AS | AI | AS | Cn:
				opcode == subb ? NEG_B | PI | AS | AI | AS:
				opcode == sub ? NEG_B | PI | AS | AI | AS | Cn:
				0:
			TYPE_ABS ?
				opcode == load ? BUF_B | MI | LS:
				opcode == add ? BUF_B | MI | LS:
				opcode == addc ? BUF_B | MI | LS:
				opcode == sub ? BUF_B | MI | LS:
				opcode == subb ? BUF_B | MI | LS:
				0:
			0:
		counter == 5 ?
			TYPE_ABS ?
				opcode == load ? AI:
				opcode == add ? BUF_B | PI | AS | AI:
				opcode == addc ? BUF_B | PI | AS | AI | Cn:
				opcode == subb ? NEG_B | PI | AS | AI:
				opcode == sub ? NEG_B | PI | AS | AI | Cn:
				0:
			0:
		0;

    assign cAI = decode[0];
    assign cAS = decode[1];
    assign cPI = decode[2];
    assign cPS = decode[3];
    assign cMI = decode[4];
    assign cRI = decode[5];
    assign cES = decode[6];
    assign cCn = decode[7];
    assign cLS = decode[8];
	assign cII = decode[9];
    assign cL = decode[14:10];
endmodule


module testbench;
	parameter WIDTH = 8;

    wire [WIDTH - 1:0] mem_input_bus;
    wire [WIDTH - 1:0] accumulator_bus;
    wire [WIDTH - 1:0] ram_read_bus;
    wire [WIDTH - 1:0] ram_write_bus;
    wire [WIDTH - 1:0] alu_out_bus;
    wire [3:0] psr_bus;

    reg clk;
    reg reset;
    reg [7:0] inst;

    wire AI, AS;
    wire PI, PS;
    wire MI, RI;
    wire ES;
    wire C_in;
	wire LS;
	wire II;
    wire [3:0] L;

    alu16 #(WIDTH) alu (clk, reset, accumulator_bus, ram_read_bus, alu_out_bus, L, LS, C_in, PI, PS, psr_bus);

    // ES == 0 -> ALU
    // ES == 1 -> PSR
    assign ram_write_bus = ES ? psr_bus: alu_out_bus;

    sync_mux_2x1 #(WIDTH) rega_mux(clk, reset, AS, AI, ram_read_bus, ram_write_bus, accumulator_bus);
    
    wire [WIDTH - 1:0] mar;
    memory #(WIDTH) ram(clk, reset, MI, RI, ram_write_bus, ram_read_bus, mar);

    wire [15:0] decode;
	wire [2:0] counter;
    controlunit cu(clk, reset, inst, AI, AS, PI, PS, MI, RI, ES, C_in, L, LS, II, decode, counter);

	always @(posedge clk or negedge reset) begin
		if (reset == 1)
			inst <= 0;
		else if (II == 1)
			inst <= ram_read_bus;
	end

    always @(posedge reset) begin
        inst <= 0;
    end
	
    initial begin
		inst = 0;
        clk = 0;
        reset = 1;
		
        while (~inst) begin
            #10 clk = ~clk;
            if (reset == 1 & clk)
                reset = 0;
        end
    end

    initial begin
        $dumpfile ("testbench.vcd");
        $dumpvars (0, testbench);
        $monitor ($time, ":\tclk=%B | reset=%B | step=%D | RAM_WRITE=%B:%D | RAM_READ=%B:%D | MAR=%B:%D | REG=%B:%D | decode=%B | Inst=%B", clk, reset, counter, ram_write_bus, ram_write_bus, ram_read_bus, ram_read_bus, mar, mar, accumulator_bus, accumulator_bus, decode, inst);
        // $monitor ($time, ":\tclk=%B | A=%B | B=%B | C=%B", clk, a, b, c);
        // #10 MI = 1; RI = 0; ram_write_bus = 1;
        // #20 MI = 1; RI = 0; ram_write_bus = 2;
        // #20 MI = 0; RI = 1; ram_write_bus = 3;
        // #20 MI = 1; ram_write_bus = 10;
        // #20 RI = 1; ram_write_bus = 1;
        // #20 MI = 1; ram_write_bus = 2;

        // #5 s = 1; a = 100; b = 0; e = 1;
        // #5 s = 0; b = 20;
        // #5 s = 1; b = 1;
        // #5 s = 1; b = 2;
        // #5 s = 1; b = 3;
        
        // ram_read_bus = 0; ram

        // #5 B = 8'd255; A = 0; L = 15;
        // #5 A = 10; B = 0; L = 4'b1100;	// Buff A
        // #5 A = 10; B = 0; L = 4'b0011;	// Neg A
        // #5 A = 10; B = 0; L = 4'b1010;	// Buff B
        // #5 A = 10; B = 0; L = 4'b0101;	// Neg B

        #2000
        $finish;
    end
endmodule

testbench.vcd
$date
	Sun Nov 26 20:28:09 2023
$end
$version
	Icarus Verilog
$end
$timescale
	1s
$end
$scope module testbench $end
$var wire 8 ! ram_write_bus [7:0] $end
$var wire 8 " ram_read_bus [7:0] $end
$var wire 4 # psr_bus [3:0] $end
$var wire 8 $ mar [7:0] $end
$var wire 16 % decode [15:0] $end
$var wire 3 & counter [2:0] $end
$var wire 8 ' alu_out_bus [7:0] $end
$var wire 8 ( accumulator_bus [7:0] $end
$var wire 1 ) RI $end
$var wire 1 * PS $end
$var wire 1 + PI $end
$var wire 1 , MI $end
$var wire 1 - LS $end
$var wire 4 . L [3:0] $end
$var wire 1 / II $end
$var wire 1 0 ES $end
$var wire 1 1 C_in $end
$var wire 1 2 AS $end
$var wire 1 3 AI $end
$var parameter 32 4 WIDTH $end
$var reg 1 5 clk $end
$var reg 8 6 inst [7:0] $end
$var reg 1 7 reset $end
$scope module alu $end
$var wire 1 5 clk $end
$var wire 1 7 reset $end
$var wire 9 8 tE [8:0] $end
$var wire 8 9 lB [7:0] $end
$var wire 8 : lA [7:0] $end
$var wire 1 * PS $end
$var wire 1 + PI $end
$var wire 1 - LS $end
$var wire 4 ; L [3:0] $end
$var wire 8 < E [7:0] $end
$var wire 1 1 Cn $end
$var wire 8 = B [7:0] $end
$var wire 8 > A [7:0] $end
$var parameter 32 ? WIDTH $end
$var reg 4 @ psr [3:0] $end
$scope begin genblk1[0] $end
$var parameter 2 A i $end
$upscope $end
$scope begin genblk1[1] $end
$var parameter 2 B i $end
$upscope $end
$scope begin genblk1[2] $end
$var parameter 3 C i $end
$upscope $end
$scope begin genblk1[3] $end
$var parameter 3 D i $end
$upscope $end
$scope begin genblk1[4] $end
$var parameter 4 E i $end
$upscope $end
$scope begin genblk1[5] $end
$var parameter 4 F i $end
$upscope $end
$scope begin genblk1[6] $end
$var parameter 4 G i $end
$upscope $end
$scope begin genblk1[7] $end
$var parameter 4 H i $end
$upscope $end
$upscope $end
$scope module cu $end
$var wire 1 I TYPE_ABS $end
$var wire 1 J TYPE_IMM $end
$var wire 1 K TYPE_OFF $end
$var wire 1 L TYPE_REG $end
$var wire 1 5 clk $end
$var wire 8 M inst [7:0] $end
$var wire 1 7 reset $end
$var wire 6 N opcode [5:0] $end
$var wire 16 O decode [15:0] $end
$var wire 1 ) cRI $end
$var wire 1 * cPS $end
$var wire 1 + cPI $end
$var wire 1 , cMI $end
$var wire 1 - cLS $end
$var wire 4 P cL [3:0] $end
$var wire 1 / cII $end
$var wire 1 0 cES $end
$var wire 1 1 cCn $end
$var wire 1 2 cAS $end
$var wire 1 3 cAI $end
$var parameter 32 Q AI $end
$var parameter 33 R AS $end
$var parameter 14 S BUF_A $end
$var parameter 14 T BUF_B $end
$var parameter 39 U Cn $end
$var parameter 38 V ES $end
$var parameter 40 W GEN_0 $end
$var parameter 40 X GEN_1 $end
$var parameter 41 Y II $end
$var parameter 40 Z LS $end
$var parameter 36 [ MI $end
$var parameter 14 \ NEG_A $end
$var parameter 14 ] NEG_B $end
$var parameter 34 ^ PI $end
$var parameter 35 _ PS $end
$var parameter 37 ` RI $end
$var parameter 6 a add $end
$var parameter 6 b addc $end
$var parameter 6 c jump $end
$var parameter 6 d jumpc $end
$var parameter 6 e jumpn $end
$var parameter 6 f jumpz $end
$var parameter 6 g load $end
$var parameter 6 h loadi $end
$var parameter 6 i store $end
$var parameter 6 j sub $end
$var parameter 6 k subb $end
$var reg 3 l counter [2:0] $end
$upscope $end
$scope module ram $end
$var wire 1 , MI $end
$var wire 1 ) RI $end
$var wire 1 5 clk $end
$var wire 8 m mar [7:0] $end
$var wire 8 n read [7:0] $end
$var wire 1 7 reset $end
$var wire 8 o write [7:0] $end
$var parameter 32 p WIDTH $end
$var parameter 38 q abs $end
$var parameter 5 r adc $end
$var parameter 38 s adca $end
$var parameter 5 t add $end
$var parameter 38 u adda $end
$var parameter 32 v count $end
$var parameter 32 w first $end
$var parameter 38 x imm $end
$var parameter 5 y jump $end
$var parameter 5 z jumpc $end
$var parameter 5 { jumpn $end
$var parameter 5 | jumpz $end
$var parameter 38 } loada $end
$var parameter 5 ~ loadi $end
$var parameter 38 !" off $end
$var parameter 5 "" sbb $end
$var parameter 38 #" sbba $end
$var parameter 32 $" second $end
$var parameter 38 %" store $end
$var parameter 5 &" sub $end
$var parameter 38 '" suba $end
$var parameter 32 (" tmp $end
$var reg 8 )" mem_addr_reg [7:0] $end
$var integer 32 *" finish [31:0] $end
$var integer 32 +" i [31:0] $end
$var integer 32 ," org [31:0] $end
$var integer 32 -" start [31:0] $end
$upscope $end
$scope module rega_mux $end
$var wire 1 5 clk $end
$var wire 1 3 enable $end
$var wire 8 ." in0 [7:0] $end
$var wire 8 /" in1 [7:0] $end
$var wire 1 7 reset $end
$var wire 1 2 sel $end
$var parameter 32 0" WIDTH $end
$var reg 8 1" out [7:0] $end
$upscope $end
$upscope $end
$enddefinitions $end
$comment Show the parameter values. $end
$dumpall
b1000 0"
b1010 ("
b1001011 '"
b1011 &"
b1000010 %"
b1100 $"
b1001010 #"
b1010 ""
b10000000 !"
b1 ~
b1000001 }
b101 |
b111 {
b110 z
b100 y
b0 x
b1011 w
b1101 v
b1001000 u
b1000 t
b1001001 s
b1001 r
b1000000 q
b1000 p
b1010 k
b1011 j
b10 i
b1 h
b1 g
b101 f
b111 e
b110 d
b100 c
b1001 b
b1000 a
b100000 `
b1000 _
b100 ^
b1010000000000 ]
b110000000000 \
b10000 [
b100000000 Z
b1000000000 Y
b11110100000000 X
b100000000 W
b1000000 V
b10000000 U
b10100000000000 T
b11000000000000 S
b10 R
b1 Q
b111 H
b110 G
b101 F
b100 E
b11 D
b10 C
b1 B
b0 A
b1000 ?
b1000 4
$end
#0
$dumpvars
b0 1"
b0 /"
b1100011 ."
b1100100 -"
b1101010 ,"
b10000000 +"
b1101000 *"
b0 )"
b0 o
b1100011 n
b0 m
b0 l
b0 P
b100010000 O
b0 N
b0 M
0L
0K
1J
0I
b0 @
b0 >
b1100011 =
b0 <
b0 ;
b0 :
b0 9
b0 8
17
b0 6
05
03
02
01
00
0/
b0 .
1-
1,
0+
0*
0)
b0 (
b0 '
b0 &
b100010000 %
b0 $
b0 #
b1100011 "
b0 !
$end
#10
07
15
#20
b1100011 9
b1100100 !
b1100100 o
b1100100 /"
b1100100 '
b1100100 <
b1100100 8
b1010 .
b1010 ;
b1010 P
1)
11
b10100110110000 %
b10100110110000 O
b1 &
b1 l
05
#30
b1000010 !
b1000010 o
b1000010 /"
b1000010 '
b1000010 <
b1000010 8
b1000001 9
b1000001 "
b1000001 =
b1000001 n
b1000001 ."
b1100100 $
b1100100 m
b1100100 )"
15
#40
b0 9
b0 !
b0 o
b0 /"
b0 '
b0 <
b0 8
b0 .
b0 ;
b0 P
0)
01
1/
b1100010000 %
b1100010000 O
b10 &
b10 l
05
#50
0J
1I
b1 N
b1100100 "
b1100100 =
b1100100 n
b1100100 ."
b0 $
b0 m
b0 )"
b1000001 6
b1000001 M
15
#60
b1100100 9
b1100101 !
b1100101 o
b1100101 /"
b1100101 '
b1100101 <
b1100101 8
b1010 .
b1010 ;
b1010 P
1)
11
0/
b10100110110000 %
b10100110110000 O
b11 &
b11 l
05
#70
b1110 !
b1110 o
b1110 /"
b1110 '
b1110 <
b1110 8
b1101 9
b1101 "
b1101 =
b1101 n
b1101 ."
b1100101 $
b1100101 m
b1100101 )"
15
#80
b1101 !
b1101 o
b1101 /"
b1101 '
b1101 <
b1101 8
0)
01
b10100100010000 %
b10100100010000 O
b100 &
b100 l
05
#90
b1010 !
b1010 o
b1010 /"
b1010 '
b1010 <
b1010 8
b1010 9
b1010 "
b1010 =
b1010 n
b1010 ."
b1101 $
b1101 m
b1101 )"
15
#100
b0 !
b0 o
b0 /"
b0 '
b0 <
b0 8
b0 9
b0 .
b0 ;
b0 P
13
0,
0-
b1 %
b1 O
b101 &
b101 l
05
#110
b1010 !
b1010 o
b1010 /"
b1010 '
b1010 <
b1010 8
b1010 :
b1010 (
b1010 >
b1010 1"
15
#120
03
b0 %
b0 O
b110 &
b110 l
05
#130
15
#140
b111 &
b111 l
05
#150
15
#160
b0 !
b0 o
b0 /"
b0 '
b0 <
b0 8
b0 :
1,
1-
b100010000 %
b100010000 O
b0 &
b0 l
05
#170
b1100101 "
b1100101 =
b1100101 n
b1100101 ."
b0 $
b0 m
b0 )"
15
#180
b1100101 9
b1100110 !
b1100110 o
b1100110 /"
b1100110 '
b1100110 <
b1100110 8
b1010 .
b1010 ;
b1010 P
1)
11
b10100110110000 %
b10100110110000 O
b1 &
b1 l
05
#190
b1100 !
b1100 o
b1100 /"
b1100 '
b1100 <
b1100 8
b1011 9
b1011 "
b1011 =
b1011 n
b1011 ."
b1100110 $
b1100110 m
b1100110 )"
15
#200
b0 9
b0 !
b0 o
b0 /"
b0 '
b0 <
b0 8
b0 .
b0 ;
b0 P
0)
01
1/
b1100010000 %
b1100010000 O
b10 &
b10 l
05
#210
1J
0I
b1011 N
b1100110 "
b1100110 =
b1100110 n
b1100110 ."
b0 $
b0 m
b0 )"
b1011 6
b1011 M
15
#220
b1100110 9
b1100111 !
b1100111 o
b1100111 /"
b1100111 '
b1100111 <
b1100111 8
b1010 .
b1010 ;
b1010 P
1)
11
0/
b10100110110000 %
b10100110110000 O
b11 &
b11 l
05
#230
b1011 !
b1011 o
b1011 /"
b1011 '
b1011 <
b1011 8
b1010 9
b1010 "
b1010 =
b1010 n
b1010 ."
b1100111 $
b1100111 m
b1100111 )"
15
#240
b11110101 9
b0 !
b0 o
b0 /"
b0 '
b0 <
b100000000 8
b1010 :
b101 .
b101 ;
b101 P
13
12
1+
0,
0)
0-
b1010010000111 %
b1010010000111 O
b100 &
b100 l
05
#250
b11110110 !
b11110110 o
b11110110 /"
b11110110 '
b11110110 <
b11110110 8
b0 :
b0 (
b0 >
b0 1"
15
#260
b0 9
b0 !
b0 o
b0 /"
b0 '
b0 <
b0 8
b0 .
b0 ;
b0 P
03
02
0+
01
b0 %
b0 O
b101 &
b101 l
05
#270
15
#280
b110 &
b110 l
05
#290
15
#300
b111 &
b111 l
05
#310
15
#320
1,
1-
b100010000 %
b100010000 O
b0 &
b0 l
05
#330
b1100111 "
b1100111 =
b1100111 n
b1100111 ."
b0 $
b0 m
b0 )"
15
#340
b1100111 9
b1101000 !
b1101000 o
b1101000 /"
b1101000 '
b1101000 <
b1101000 8
b1010 .
b1010 ;
b1010 P
1)
11
b10100110110000 %
b10100110110000 O
b1 &
b1 l
05
#350
b0 !
b0 o
b0 /"
b0 '
b0 <
b100000000 8
b11111111 9
b11111111 "
b11111111 =
b11111111 n
b11111111 ."
b1101000 $
b1101000 m
b1101000 )"
15
#360
b0 9
b0 !
b0 o
b0 /"
b0 '
b0 <
b0 8
b0 .
b0 ;
b0 P
0)
01
1/
b1100010000 %
b1100010000 O
b10 &
b10 l
05
#370
0J
0I
1L
b111111 N
b1101000 "
b1101000 =
b1101000 n
b1101000 ."
b0 $
b0 m
b0 )"
b11111111 6
b11111111 M
15
#380
b1101000 9
b1101001 !
b1101001 o
b1101001 /"
b1101001 '
b1101001 <
b1101001 8
b1010 .
b1010 ;
b1010 P
1)
11
0/
b10100110110000 %
b10100110110000 O
b11 &
b11 l
05
