tiny.sv


module alu16 #(parameter WIDTH = 16) (clk, reset, A, B, E, L, LS, Cn, PI, PS, psr);
    input [WIDTH - 1:0] A, B;
    input [3:0] L;
    input Cn;
    input clk;
    input reset;
	input LS;
    input PI, PS;

    output [WIDTH - 1:0] E;
    output reg [3:0] psr;

    wire [WIDTH - 1:0] lA;
    wire [WIDTH - 1:0] lB;
    wire [WIDTH:0] tE;

	genvar i;

	for (i = 0; i < WIDTH; i = i + 1)
		assign lB[i] = A[i] ? (B[i] ? L[3] : L[2]) : (B[i] ? L[1] : L[0]);

	assign lA = LS ? 0: A;
    assign tE = { 1'b0, lA } + { 1'b0, lB } + (1 & Cn);
    assign E = tE[WIDTH - 1:0];

    always @(posedge clk or posedge reset) begin
        if (reset == 1) begin
            psr <= 0;
        end
        else
        if (PI == 1) begin
            if (PS == 1) begin
                psr <= tE[3:0];
            end
            else begin
                psr[0] <= tE[16];
                psr[1] <= tE[WIDTH - 1];
                psr[2] <= (tE == 0) ? 1: 0;
                psr[3] <= (E[WIDTH - 1] & ~A[WIDTH - 1] & ~lB[WIDTH - 1]) | (~E[WIDTH - 1] & A[WIDTH - 1] & lB[WIDTH - 1]);
            end	
        end
    end
endmodule


module memory #(parameter WIDTH = 16) (clk, reset, MI, RI, write, read, mar);
    input clk, MI, RI;
    input reset;
    
    output [WIDTH - 1:0] mar;
    input [WIDTH - 1:0] write;
    output [WIDTH - 1:0] read;
    
    reg [WIDTH - 1:0] mem_addr_reg;
    reg [WIDTH - 1:0] ram [2**16-1:0];
    
    integer i;

    assign mar = mem_addr_reg;
	
	// assign TYPE_IMM = ~inst[7] & ~inst[6];	// 0
	// assign TYPE_ABS = ~inst[7] & inst[6];	// 1
	// assign TYPE_OFF = inst[7] & ~inst[6];	// 2
	// assign TYPE_REG = inst[7] & inst[6];	// 3
	
	parameter imm = 0 << 6;
	parameter abs = 1 << 6;
	parameter off = 2 << 6;

	parameter load 	= 	5'b00001;

	parameter store = 	5'b00010;

	parameter jump 	= 	5'b00100;
	parameter jumpz =	5'b00101;
	parameter jumpc =	5'b00110;
	parameter jumpn =	5'b00111;
	
	parameter add 	= 	5'b01000;
	parameter addc 	= 	5'b01001;
	parameter subb 	= 	5'b01010;
	parameter sub 	= 	5'b01011;

    always @(posedge clk or posedge reset) begin
        if (reset == 1) begin
            mem_addr_reg <= 0;

            for (i = 0; i < 2**(WIDTH - 1); i = i + 1)
                ram[i] = 0;

			ram[0] = 99;

			ram[100] = 8'h01;
			ram[101] = 4;
			
			ram[102] = 8'hff;
			ram[103] = 4;
        end
        else
        begin
            if (MI == 1)
                mem_addr_reg <= write;

            if (RI == 1)
                ram[mem_addr_reg] <= write;
        end
    end

    assign read = ram[mem_addr_reg];
endmodule


module sync_mux_2x1 #(parameter WIDTH = 16) (clk, reset, sel, enable, in0, in1, out);
    input sel, enable, clk, reset;
    input [WIDTH - 1:0] in0, in1;

    output reg [WIDTH - 1:0] out;

    always @(posedge clk or posedge reset) begin
        if (reset == 1)
            out = 0;
        else
        if (enable) begin
            if (sel == 1)
                out = in1;
            else
                out = in0;
        end
    end
endmodule

module controlunit(clk, reset, inst, cAI, cAS, cPI, cPS, cMI, cRI, cES, cCn, cL, cLS, cII, decode, counter);
	// Enable Control Lines

    parameter AI = 1 << 0;
    parameter AS = 1 << 1;
    parameter PI = 1 << 2;
    parameter PS = 1 << 3;
    parameter MI = 1 << 4;
    parameter RI = 1 << 5;
    parameter ES = 1 << 6;
    parameter Cn = 1 << 7;
    parameter LS = 1 << 8;
    parameter II = 1 << 9;

	// ALU Control Liines

    parameter GEN_0 = 14'b0000_0000000000 | LS;
    parameter GEN_1 = 14'b1111_0000000000 | LS;
    parameter BUF_A = 14'b1100_0000000000 | LS;
    parameter NEG_A = 14'b0011_0000000000 | LS;
    parameter BUF_B = 14'b1010_0000000000 | LS;
    parameter NEG_B = 14'b0101_0000000000 | LS;

    // parameter NAND = 14'b0111_0000000000 | LS;
    // parameter AND = 14'b1000_0000000000 | LS;
    // parameter OR = 14'b1110_0000000000 | LS;
    // parameter NOR = 14'b0001_0000000000 | LS;
    // parameter XOR = 14'b0110_0000000000 | LS;
    // parameter XNOR = 14'b1001_0000000000 | LS;

	// parameter INC_A = BUF_A | Cn | LS;
	// parameter DEC_A = NEG_A | LS;

	// parameter INC_B = BUF_B | Cn | LS;
	// parameter DEC_B = NEG_B | LS;

    // parameter ADD = BUF_B;
	// parameter ADC = BUF_B | Cn;
	// parameter SUB = NEG_B | Cn;
	// parameter SBB = NEG_B;
	
	// parameter INST_IMM = 1;
	// parameter INST_ABS = 2;
	// parameter INST_OFF = 3;
	
	// // Instructions
	// parameter NOP = 8'b0;
	
	// parameter INST_TYPE_REG = 0;
	// parameter INST_TYPE_IMM = 1;
	// parameter INST_TYPE_ABS = 2;
	// parameter INST_TYPE_OFF = 3;

	// ALU INT - ADDRESSING_TYPE[2] - INST_TYPE[]

	parameter load 	= 	6'b000001;
	parameter loadi 	= 	6'b000001;

	parameter store = 	6'b000010;

	parameter jump 	= 	6'b000100;
	parameter jumpz =	6'b000101;
	parameter jumpc =	6'b000110;
	parameter jumpn =	6'b000111;
	
	parameter add 	= 	6'b001000;
	parameter addc 	= 	6'b001001;
	parameter subb 	= 	6'b001010;
	parameter sub 	= 	6'b001011;

	input clk;
    input reset;
    input [7:0] inst;

    output wire cAI, cAS;
    output wire cPI, cPS;
    output wire cMI, cRI;
    output wire cES;
    output wire cCn;
    output wire cLS;
    output wire cII;
    output wire [3:0] cL;
    
    output reg [14:0] decode;
    output reg [3:0] counter;

    reg reset_counter;
	
	wire TYPE_REG, TYPE_IMM, TYPE_ABS, TYPE_OFF;
	wire [5:0] opcode;
	
	assign TYPE_IMM = ~inst[7] & ~inst[6];	// 0
	assign TYPE_ABS = ~inst[7] & inst[6];	// 1
	assign TYPE_OFF = inst[7] & ~inst[6];	// 2
	assign TYPE_REG = inst[7] & inst[6];	// 3

	assign opcode = inst[5:0];

    always @(negedge clk or posedge reset) begin
        if (reset == 1) begin
            counter <= 0;
            decode <= 0;
            reset_counter <= 0;
        end else begin
			if (reset_counter == 1) begin
                counter <= 0;
                decode <= 0;
                reset_counter <= 0;
			end else begin				
				case (counter)
					4'h0:
						decode <= GEN_0 | MI;

					4'h1:
						decode <= BUF_B | Cn | MI | RI;

					4'h2:
						decode <= II | GEN_0 | MI;

					4'h3:
						decode <= BUF_B | Cn | MI | RI;

					4'h4: begin
						reset_counter <= 1;
					end
				endcase

				// if (TYPE_IMM)
				// 	case (counter)
				// 		4'h4:
				// 			decode <= 
				// 	endcase

				if (reset_counter == 1)
					counter <= 0;
				else
					counter <= counter + 1;
			end
        end
    end
    
    assign cAI = decode[0];
    assign cAS = decode[1];
    assign cPI = decode[2];
    assign cPS = decode[3];
    assign cMI = decode[4];
    assign cRI = decode[5];
    assign cES = decode[6];
    assign cCn = decode[7];
    assign cLS = decode[8];
	assign cII = decode[9];
    assign cL = decode[14:10];
endmodule


module testbench;
	parameter WIDTH = 8;

    wire [WIDTH - 1:0] mem_input_bus;
    wire [WIDTH - 1:0] accumulator_bus;
    wire [WIDTH - 1:0] ram_read_bus;
    wire [WIDTH - 1:0] ram_write_bus;
    wire [WIDTH - 1:0] alu_out_bus;
    wire [3:0] psr_bus;

    reg clk;
    reg reset;
    reg [7:0] inst;

    wire AI, AS;
    wire PI, PS;
    wire MI, RI;
    wire ES;
    wire C_in;
	wire LS;
	wire II;
    wire [3:0] L;

    alu16 #(WIDTH) alu (clk, reset, accumulator_bus, ram_read_bus, alu_out_bus, L, LS, C_in, PI, PS, psr_bus);

    // ES == 0 -> ALU
    // ES == 1 -> PSR
    assign ram_write_bus = ES ? psr_bus: alu_out_bus;

    sync_mux_2x1 #(WIDTH) rega_mux(clk, reset, AS, AI, ram_read_bus, ram_write_bus, accumulator_bus);
    
    wire [WIDTH - 1:0] mar;
    memory #(WIDTH) ram(clk, reset, MI, RI, ram_write_bus, ram_read_bus, mar);
    
    wire [14:0] decode;
	wire [3:0] counter;
    controlunit cu(clk, reset, inst, AI, AS, PI, PS, MI, RI, ES, C_in, L, LS, II, decode, counter);

	always @(posedge clk or negedge reset) begin
		if (reset == 1)
			inst <= 0;
		else if (II == 1)
			inst <= ram_read_bus;
	end

    always @(posedge reset) begin
        inst <= 0;
    end
	
    initial begin
		inst = 0;
        clk = 0;
        reset = 1;
		
        while (~inst) begin
            #10 clk = ~clk;
            if (reset == 1 & clk)
                reset = 0;
        end
    end

    initial begin
        $dumpfile ("testbench.vcd");
        $dumpvars (0, testbench);
        $monitor ($time, ":\tclk=%B | reset=%B | step=%D | RAM_WRITE=%B:%D | RAM_READ=%B:%D | MAR=%B:%D | REG=%B:%D | decode=%B | Inst=%B", clk, reset, counter, ram_write_bus, ram_write_bus, ram_read_bus, ram_read_bus, mar, mar, accumulator_bus, accumulator_bus, decode, inst);
        // $monitor ($time, ":\tclk=%B | A=%B | B=%B | C=%B", clk, a, b, c);
        // #10 MI = 1; RI = 0; ram_write_bus = 1;
        // #20 MI = 1; RI = 0; ram_write_bus = 2;
        // #20 MI = 0; RI = 1; ram_write_bus = 3;
        // #20 MI = 1; ram_write_bus = 10;
        // #20 RI = 1; ram_write_bus = 1;
        // #20 MI = 1; ram_write_bus = 2;

        // #5 s = 1; a = 100; b = 0; e = 1;
        // #5 s = 0; b = 20;
        // #5 s = 1; b = 1;
        // #5 s = 1; b = 2;
        // #5 s = 1; b = 3;
        
        // ram_read_bus = 0; ram

        // #5 B = 8'd255; A = 0; L = 15;
        // #5 A = 10; B = 0; L = 4'b1100;	// Buff A
        // #5 A = 10; B = 0; L = 4'b0011;	// Neg A
        // #5 A = 10; B = 0; L = 4'b1010;	// Buff B
        // #5 A = 10; B = 0; L = 4'b0101;	// Neg B

        #2000
        $finish;
    end
endmodule

testbench.vcd
$date
	Sun Nov 26 17:40:17 2023
$end
$version
	Icarus Verilog
$end
$timescale
	1s
$end
$scope module testbench $end
$var wire 8 ! ram_write_bus [7:0] $end
$var wire 8 " ram_read_bus [7:0] $end
$var wire 4 # psr_bus [3:0] $end
$var wire 8 $ mar [7:0] $end
$var wire 15 % decode [14:0] $end
$var wire 4 & counter [3:0] $end
$var wire 8 ' alu_out_bus [7:0] $end
$var wire 8 ( accumulator_bus [7:0] $end
$var wire 1 ) RI $end
$var wire 1 * PS $end
$var wire 1 + PI $end
$var wire 1 , MI $end
$var wire 1 - LS $end
$var wire 4 . L [3:0] $end
$var wire 1 / II $end
$var wire 1 0 ES $end
$var wire 1 1 C_in $end
$var wire 1 2 AS $end
$var wire 1 3 AI $end
$var parameter 32 4 WIDTH $end
$var reg 1 5 clk $end
$var reg 8 6 inst [7:0] $end
$var reg 1 7 reset $end
$scope module alu $end
$var wire 1 5 clk $end
$var wire 1 7 reset $end
$var wire 9 8 tE [8:0] $end
$var wire 8 9 lB [7:0] $end
$var wire 8 : lA [7:0] $end
$var wire 1 * PS $end
$var wire 1 + PI $end
$var wire 1 - LS $end
$var wire 4 ; L [3:0] $end
$var wire 8 < E [7:0] $end
$var wire 1 1 Cn $end
$var wire 8 = B [7:0] $end
$var wire 8 > A [7:0] $end
$var parameter 32 ? WIDTH $end
$var reg 4 @ psr [3:0] $end
$scope begin genblk1[0] $end
$var parameter 2 A i $end
$upscope $end
$scope begin genblk1[1] $end
$var parameter 2 B i $end
$upscope $end
$scope begin genblk1[2] $end
$var parameter 3 C i $end
$upscope $end
$scope begin genblk1[3] $end
$var parameter 3 D i $end
$upscope $end
$scope begin genblk1[4] $end
$var parameter 4 E i $end
$upscope $end
$scope begin genblk1[5] $end
$var parameter 4 F i $end
$upscope $end
$scope begin genblk1[6] $end
$var parameter 4 G i $end
$upscope $end
$scope begin genblk1[7] $end
$var parameter 4 H i $end
$upscope $end
$upscope $end
$scope module cu $end
$var wire 1 I TYPE_ABS $end
$var wire 1 J TYPE_IMM $end
$var wire 1 K TYPE_OFF $end
$var wire 1 L TYPE_REG $end
$var wire 1 5 clk $end
$var wire 8 M inst [7:0] $end
$var wire 1 7 reset $end
$var wire 6 N opcode [5:0] $end
$var wire 1 ) cRI $end
$var wire 1 * cPS $end
$var wire 1 + cPI $end
$var wire 1 , cMI $end
$var wire 1 - cLS $end
$var wire 4 O cL [3:0] $end
$var wire 1 / cII $end
$var wire 1 0 cES $end
$var wire 1 1 cCn $end
$var wire 1 2 cAS $end
$var wire 1 3 cAI $end
$var parameter 32 P AI $end
$var parameter 33 Q AS $end
$var parameter 40 R BUF_A $end
$var parameter 40 S BUF_B $end
$var parameter 39 T Cn $end
$var parameter 38 U ES $end
$var parameter 40 V GEN_0 $end
$var parameter 40 W GEN_1 $end
$var parameter 41 X II $end
$var parameter 40 Y LS $end
$var parameter 36 Z MI $end
$var parameter 40 [ NEG_A $end
$var parameter 40 \ NEG_B $end
$var parameter 34 ] PI $end
$var parameter 35 ^ PS $end
$var parameter 37 _ RI $end
$var parameter 6 ` add $end
$var parameter 6 a addc $end
$var parameter 6 b jump $end
$var parameter 6 c jumpc $end
$var parameter 6 d jumpn $end
$var parameter 6 e jumpz $end
$var parameter 6 f load $end
$var parameter 6 g loadi $end
$var parameter 6 h store $end
$var parameter 6 i sub $end
$var parameter 6 j subb $end
$var reg 4 k counter [3:0] $end
$var reg 15 l decode [14:0] $end
$var reg 1 m reset_counter $end
$upscope $end
$scope module ram $end
$var wire 1 , MI $end
$var wire 1 ) RI $end
$var wire 1 5 clk $end
$var wire 8 n mar [7:0] $end
$var wire 8 o read [7:0] $end
$var wire 1 7 reset $end
$var wire 8 p write [7:0] $end
$var parameter 32 q WIDTH $end
$var parameter 38 r abs $end
$var parameter 5 s add $end
$var parameter 5 t addc $end
$var parameter 38 u imm $end
$var parameter 5 v jump $end
$var parameter 5 w jumpc $end
$var parameter 5 x jumpn $end
$var parameter 5 y jumpz $end
$var parameter 5 z load $end
$var parameter 38 { off $end
$var parameter 5 | store $end
$var parameter 5 } sub $end
$var parameter 5 ~ subb $end
$var reg 8 !" mem_addr_reg [7:0] $end
$var integer 32 "" i [31:0] $end
$upscope $end
$scope module rega_mux $end
$var wire 1 5 clk $end
$var wire 1 3 enable $end
$var wire 8 #" in0 [7:0] $end
$var wire 8 $" in1 [7:0] $end
$var wire 1 7 reset $end
$var wire 1 2 sel $end
$var parameter 32 %" WIDTH $end
$var reg 8 &" out [7:0] $end
$upscope $end
$upscope $end
$enddefinitions $end
$comment Show the parameter values. $end
$dumpall
b1000 %"
b1010 ~
b1011 }
b10 |
b10000000 {
b1 z
b101 y
b111 x
b110 w
b100 v
b0 u
b1001 t
b1000 s
b1000000 r
b1000 q
b1010 j
b1011 i
b10 h
b1 g
b1 f
b101 e
b111 d
b110 c
b100 b
b1001 a
b1000 `
b100000 _
b1000 ^
b100 ]
b1010100000000 \
b110100000000 [
b10000 Z
b100000000 Y
b1000000000 X
b11110100000000 W
b100000000 V
b1000000 U
b10000000 T
b10100100000000 S
b11000100000000 R
b10 Q
b1 P
b111 H
b110 G
b101 F
b100 E
b11 D
b10 C
b1 B
b0 A
b1000 ?
b1000 4
$end
#0
$dumpvars
b0 &"
b0 $"
b1100011 #"
b10000000 ""
b0 !"
b0 p
b1100011 o
b0 n
0m
b0 l
b0 k
b0 O
b0 N
b0 M
0L
0K
1J
0I
b0 @
b0 >
b1100011 =
b0 <
b0 ;
b0 :
b0 9
b0 8
17
b0 6
05
03
02
01
00
0/
b0 .
0-
0,
0+
0*
0)
b0 (
b0 '
b0 &
b0 %
b0 $
b0 #
b1100011 "
b0 !
$end
#10
07
15
#20
1,
1-
b1 &
b1 k
b100010000 %
b100010000 l
05
#30
15
#40
b1100011 9
b1100100 !
b1100100 p
b1100100 $"
b1100100 '
b1100100 <
b1100100 8
b1010 .
b1010 ;
b1010 O
1)
11
b10 &
b10 k
b10100110110000 %
b10100110110000 l
05
#50
b10 !
b10 p
b10 $"
b10 '
b10 <
b10 8
b1 9
b1 "
b1 =
b1 o
b1 #"
b1100100 $
b1100100 n
b1100100 !"
15
#60
b0 9
b0 !
b0 p
b0 $"
b0 '
b0 <
b0 8
b0 .
b0 ;
b0 O
0)
01
1/
b11 &
b11 k
b1100010000 %
b1100010000 l
05
#70
b1 N
b1100100 "
b1100100 =
b1100100 o
b1100100 #"
b0 $
b0 n
b0 !"
b1 6
b1 M
15
#80
b1100100 9
b1100101 !
b1100101 p
b1100101 $"
b1100101 '
b1100101 <
b1100101 8
b1010 .
b1010 ;
b1010 O
1)
11
0/
b100 &
b100 k
b10100110110000 %
b10100110110000 l
05
#90
b101 !
b101 p
b101 $"
b101 '
b101 <
b101 8
b100 9
b100 "
b100 =
b100 o
b100 #"
b1100101 $
b1100101 n
b1100101 !"
15
#100
b101 &
b101 k
1m
05
#110
b1 !
b1 p
b1 $"
b1 '
b1 <
b1 8
b0 9
b0 "
b0 =
b0 o
b0 #"
b101 $
b101 n
b101 !"
15
#120
b0 !
b0 p
b0 $"
b0 '
b0 <
b0 8
b0 .
b0 ;
b0 O
0,
0)
01
0-
0m
b0 %
b0 l
b0 &
b0 k
05
#130
15
#140
1,
1-
b1 &
b1 k
b100010000 %
b100010000 l
05
#150
b1100101 "
b1100101 =
b1100101 o
b1100101 #"
b0 $
b0 n
b0 !"
15
#160
b1100101 9
b1100110 !
b1100110 p
b1100110 $"
b1100110 '
b1100110 <
b1100110 8
b1010 .
b1010 ;
b1010 O
1)
11
b10 &
b10 k
b10100110110000 %
b10100110110000 l
05
#170
b0 !
b0 p
b0 $"
b0 '
b0 <
b100000000 8
b11111111 9
b11111111 "
b11111111 =
b11111111 o
b11111111 #"
b1100110 $
b1100110 n
b1100110 !"
15
#180
b0 9
b0 !
b0 p
b0 $"
b0 '
b0 <
b0 8
b0 .
b0 ;
b0 O
0)
01
1/
b11 &
b11 k
b1100010000 %
b1100010000 l
05
#190
0J
0I
1L
b111111 N
b1100110 "
b1100110 =
b1100110 o
b1100110 #"
b0 $
b0 n
b0 !"
b11111111 6
b11111111 M
15
#200
b1100110 9
b1100111 !
b1100111 p
b1100111 $"
b1100111 '
b1100111 <
b1100111 8
b1010 .
b1010 ;
b1010 O
1)
11
0/
b100 &
b100 k
b10100110110000 %
b10100110110000 l
05
