tiny.sv


module alu16 #(parameter WIDTH = 16) (clk, reset, A, B, E, L, LS, Cn, PI, PS, psr);
    input [WIDTH - 1:0] A, B;
    input [3:0] L;
    input Cn;
    input clk;
    input reset;
	input LS;
    input PI, PS;

    output [WIDTH - 1:0] E;
    output reg [3:0] psr;

    wire [WIDTH - 1:0] lA;
    wire [WIDTH - 1:0] lB;
    wire [WIDTH:0] tE;

	genvar i;

	for (i = 0; i < WIDTH; i = i + 1)
		assign lB[i] = A[i] ? (B[i] ? L[3] : L[2]) : (B[i] ? L[1] : L[0]);

	assign lA = LS ? 0: A;
    assign tE = { 1'b0, lA } + { 1'b0, lB } + (1 & Cn);
    assign E = tE[WIDTH - 1:0];

	// assign psr_wire[3] = (E[WIDTH - 1] & ~A[WIDTH - 1] & (lB[WIDTH - 1] == 0)) | (~E[WIDTH - 1] & A[WIDTH - 1] & lB[WIDTH - 1]);

    always @(posedge clk or negedge reset) begin
        if (reset == 1) begin
            psr <= 0;
        end
        else
        if (PI == 1) begin
			psr[0] <= tE[WIDTH];
			psr[1] <= E[WIDTH - 1];
			psr[2] <= (E[WIDTH - 1: 0] == 0) ? 1: 0;
			psr[3] <= 0;

            // if (PS == 1) begin
            // end
            // else begin
            //     psr <= psr_wire;
            // end
        end
    end
endmodule


module sync_mux_2x1 #(parameter WIDTH = 16) (clk, reset, sel, enable, in0, in1, out);
    input sel, enable, clk, reset;
    input [WIDTH - 1:0] in0, in1;

    output reg [WIDTH - 1:0] out;

    always @(posedge clk or posedge reset) begin
        if (reset == 1)
            out = 0;
        else
        if (enable) begin
            if (sel == 1)
                out = in1;
            else
                out = in0;
        end
    end
endmodule


module memory #(parameter WIDTH = 16) (clk, reset, MI, RI, write, read, mar);
    input clk, MI, RI;
    input reset;
    
    output [WIDTH - 1:0] mar;
    input [WIDTH - 1:0] write;
    output [WIDTH - 1:0] read;
    
    reg [WIDTH - 1:0] mem_addr_reg;
    reg [WIDTH - 1:0] ram [2**WIDTH - 1:0];
    
    integer i;

    assign mar = mem_addr_reg;
	
	parameter imm = 0 << 6;
	parameter abs = 1 << 6;
	parameter off = 2 << 6;

	parameter loadi	= 	5'b00001;
	parameter loada =	loadi | abs;

	parameter store = 	5'b00010 | abs;

	parameter jump 	= 	5'b00100 | abs;
	parameter jumpz =	5'b00101 | abs;
	parameter jumpc =	5'b00110 | abs;
	parameter jumpn =	5'b00111 | abs;

	parameter add 	= 	5'b01000;
	parameter adc 	= 	5'b01001;
	parameter sbb 	= 	5'b01010;
	parameter sub 	= 	5'b01011;

	parameter adda 	= 	add | abs;
	parameter adca 	= 	adc | abs;
	parameter sbba 	= 	sbb | abs;
	parameter suba 	= 	sub | abs;
		
	parameter tmp = 10;
	parameter first = 11;
	parameter second = 12;
	parameter count = 13;

	integer org, start, finish;

	wire [WIDTH - 1:0] display;
	

    always @(posedge clk or posedge reset) begin
        if (reset == 1) begin
			start = 100;
			finish = 200;
            
			mem_addr_reg <= 0;

            for (i = 0; i < 2**(WIDTH - 1); i++)
                ram[i] = 0;
			
			org = start;

			ram[0] = org - 1;

			ram[first] = 0;
			ram[second] = 1;
			ram[count] = 14;

			start = org++;

			ram[start] = loada; ram[org++] = count;
			ram[org++] = sbb; ram[org++] = 0;
			ram[org++] = store; ram[org++] = count;

			ram[org++] = jumpz; ram[org++] = finish - 1;
			
			ram[org++] = loada; ram[org++] = second;
			ram[org++] = store; ram[org++] = tmp;

			ram[org++] = adda; ram[org++] = first;
			ram[org++] = store; ram[org++] = second;

			ram[org++] = loada; ram[org++] = tmp;
			ram[org++] = store; ram[org++] = first;
			
			ram[org++] = jump; ram[org++] = start - 1;

			ram[finish] = 8'hff;
        end else begin
            if (MI == 1)
                mem_addr_reg <= write;

            if (RI == 1)
                ram[mem_addr_reg] <= write;
        end
    end

    assign read = ram[mem_addr_reg];
	assign display = ram[first];
endmodule


module controlunit(clk, reset, inst, psr, cAI, cAS, cPI, cPS, cMI, cRI, cES, cCn, cL, cLS, cII, decode, counter);
	// Enable Control Lines

    parameter AI = 1 << 0;
    parameter AS = 1 << 1;
    parameter PI = 1 << 2;
    parameter PS = 1 << 3;
    parameter MI = 1 << 4;
    parameter RI = 1 << 5;
    parameter ES = 1 << 6;
    parameter Cn = 1 << 7;
    parameter LS = 1 << 8;
    parameter II = 1 << 9;

	// ALU Control Lines

    parameter GEN_0 = 14'b0000_0000000000 | LS;
    parameter GEN_1 = 14'b1111_0000000000 | LS;
    parameter BUF_A = 14'b1100_0000000000;
    parameter NEG_A = 14'b0011_0000000000;
    parameter BUF_B = 14'b1010_0000000000;
    parameter NEG_B = 14'b0101_0000000000;

	parameter load 	= 	6'b000001;
	parameter loadi = 	6'b000001;

	parameter store = 	6'b000010;

	parameter jump 	= 	6'b000100;
	parameter jumpz =	6'b000101;
	parameter jumpc =	6'b000110;
	parameter jumpn =	6'b000111;

	parameter add 	= 	6'b001000;
	parameter addc 	= 	6'b001001;
	parameter subb 	= 	6'b001010;
	parameter sub 	= 	6'b001011;

	input clk;
    input reset;
    input [7:0] inst;
    input [3:0] psr;

    output wire cAI, cAS;
    output wire cPI, cPS;
    output wire cMI, cRI;
    output wire cES;
    output wire cCn;
    output wire cLS;
    output wire cII;
    output wire [3:0] cL;

    output [15:0] decode;
    output reg [2:0] counter;

	wire TYPE_REG, TYPE_IMM, TYPE_ABS, TYPE_OFF;
	wire [5:0] opcode;

	assign TYPE_IMM = ~inst[7] & ~inst[6];	// 0
	assign TYPE_ABS = ~inst[7] & inst[6];	// 1
	assign TYPE_OFF = inst[7] & ~inst[6];	// 2
	assign TYPE_REG = inst[7] & inst[6];	// 3

	assign opcode = inst[5:0];

    always @(negedge clk or posedge reset) begin
        if (reset == 1) begin
            counter <= 0;
        end else begin
			counter <= counter + 1;
        end
    end
	
	assign decode =
		counter == 0 ? GEN_0 | MI:
		counter == 1 ? BUF_B | Cn | MI | RI | LS:
		counter == 2 ? II | GEN_0 | MI:
		counter == 3 ? BUF_B | Cn | MI | RI | LS:
		counter == 4 ?
			TYPE_IMM ?
				opcode == load ? AI:

				opcode == add ? BUF_B | PI | AS | AI:
				opcode == addc ? BUF_B | PI | AS | AI | Cn:
				opcode == subb ? NEG_B | PI | AS | AI:
				opcode == sub ? NEG_B | PI | AS | AI | Cn:
				0:
			TYPE_ABS ?
				opcode == load ? BUF_B | MI | LS:

				opcode == store ? BUF_B | MI | LS:

				((opcode == jump) |
				((opcode == jumpz) & (psr[2] == 1)) |
				((opcode == jumpc) & (psr[0] == 1)) |
				((opcode == jumpn) & (psr[1] == 1))) ? GEN_0 | MI | AI:

				opcode == add ? BUF_B | MI | LS:
				opcode == addc ? BUF_B | MI | LS:
				opcode == sub ? BUF_B | MI | LS:
				opcode == subb ? BUF_B | MI | LS:
				0:
			0:
		counter == 5 ?
			TYPE_ABS ?
				opcode == load ? AI:

				opcode == store ? BUF_A | RI | LS:

				((opcode == jump) |
				((opcode == jumpz) & (psr[2] == 1)) |
				((opcode == jumpc) & (psr[0] == 1)) |
				((opcode == jumpn) & (psr[1] == 1))) ? BUF_A | MI | RI | LS:
				
				opcode == add ? BUF_B | PI | AS | AI:
				opcode == addc ? BUF_B | PI | AS | AI | Cn:
				opcode == subb ? NEG_B | PI | AS | AI:
				opcode == sub ? NEG_B | PI | AS | AI | Cn:
				0:
			0:
		0;
	
	always @(decode == 0) begin
		counter <= 0;
	end

    assign cAI = decode[0];
    assign cAS = decode[1];
    assign cPI = decode[2];
    assign cPS = decode[3];
    assign cMI = decode[4];
    assign cRI = decode[5];
    assign cES = decode[6];
    assign cCn = decode[7];
    assign cLS = decode[8];
	assign cII = decode[9];
    assign cL = decode[14:10];
endmodule

module processor #(parameter WIDTH = 16)(clk, reset, halt);
    wire [WIDTH - 1:0] mem_input_bus;
    wire [WIDTH - 1:0] accumulator_bus;
    wire [WIDTH - 1:0] ram_read_bus;
    wire [WIDTH - 1:0] ram_write_bus;
    wire [WIDTH - 1:0] alu_out_bus;
    wire [3:0] psr_bus;

    input clk;
    input reset;
	output reg halt;

    reg [7:0] inst;

    wire AI, AS;
    wire PI, PS;
    wire MI, RI;
    wire ES;
    wire C_in;
	wire LS;
	wire II;
    wire [3:0] L;

    alu16 #(WIDTH) alu (clk, reset, accumulator_bus, ram_read_bus, alu_out_bus, L, LS, C_in, PI, PS, psr_bus);

    // ES == 0 -> ALU
    // ES == 1 -> PSR
    assign ram_write_bus = ES ? psr_bus: alu_out_bus;

    sync_mux_2x1 #(WIDTH) rega_mux(clk, reset, AS, AI, ram_read_bus, ram_write_bus, accumulator_bus);

    wire [WIDTH - 1:0] mar;
    memory #(WIDTH) ram(clk, reset, MI, RI, ram_write_bus, ram_read_bus, mar);

    wire [15:0] decode;
	wire [2:0] counter;
    controlunit cu(clk, reset, inst, psr_bus, AI, AS, PI, PS, MI, RI, ES, C_in, L, LS, II, decode, counter);

	always @(posedge clk or posedge reset) begin
		if (reset == 1)
			inst <= 0;
		else if (II == 1) begin
			inst <= ram_read_bus;
			halt <= 0;
		end
	end

	always @(posedge clk & inst == 2**WIDTH - 1) begin
		halt <= 1;
	end
endmodule


module testbench;
	reg clk;
	reg reset;
	wire halt;

	processor #(8) tiny(clk, reset, halt);
	
    initial begin
        clk = 0;
        reset = 1;

        forever begin
            #1 clk = ~clk;
            if (reset == 1 & clk)
                reset = 0;
			else if (halt)
				$finish;
        end
    end

    initial begin
        $dumpfile ("testbench.vcd");
        $dumpvars (0, testbench);

        $monitor ($time, ":\tclk=%B | reset=%B | halt=%B", clk, reset, halt);

        #2000
        $finish;
    end
endmodule

testbench.vcd
$date
	Wed Nov 29 23:33:10 2023
$end
$version
	Icarus Verilog
$end
$timescale
	1s
$end
$scope module testbench $end
$var wire 1 ! halt $end
$var reg 1 " clk $end
$var reg 1 # reset $end
$scope module tiny $end
$var wire 1 " clk $end
$var wire 1 # reset $end
$var wire 8 $ ram_write_bus [7:0] $end
$var wire 8 % ram_read_bus [7:0] $end
$var wire 4 & psr_bus [3:0] $end
$var wire 8 ' mar [7:0] $end
$var wire 16 ( decode [15:0] $end
$var wire 3 ) counter [2:0] $end
$var wire 8 * alu_out_bus [7:0] $end
$var wire 8 + accumulator_bus [7:0] $end
$var wire 1 , RI $end
$var wire 1 - PS $end
$var wire 1 . PI $end
$var wire 1 / MI $end
$var wire 1 0 LS $end
$var wire 4 1 L [3:0] $end
$var wire 1 2 II $end
$var wire 1 3 ES $end
$var wire 1 4 C_in $end
$var wire 1 5 AS $end
$var wire 1 6 AI $end
$var parameter 32 7 WIDTH $end
$var reg 1 ! halt $end
$var reg 8 8 inst [7:0] $end
$scope module alu $end
$var wire 1 " clk $end
$var wire 1 # reset $end
$var wire 9 9 tE [8:0] $end
$var wire 8 : lB [7:0] $end
$var wire 8 ; lA [7:0] $end
$var wire 1 - PS $end
$var wire 1 . PI $end
$var wire 1 0 LS $end
$var wire 4 < L [3:0] $end
$var wire 8 = E [7:0] $end
$var wire 1 4 Cn $end
$var wire 8 > B [7:0] $end
$var wire 8 ? A [7:0] $end
$var parameter 32 @ WIDTH $end
$var reg 4 A psr [3:0] $end
$scope begin genblk1[0] $end
$var parameter 2 B i $end
$upscope $end
$scope begin genblk1[1] $end
$var parameter 2 C i $end
$upscope $end
$scope begin genblk1[2] $end
$var parameter 3 D i $end
$upscope $end
$scope begin genblk1[3] $end
$var parameter 3 E i $end
$upscope $end
$scope begin genblk1[4] $end
$var parameter 4 F i $end
$upscope $end
$scope begin genblk1[5] $end
$var parameter 4 G i $end
$upscope $end
$scope begin genblk1[6] $end
$var parameter 4 H i $end
$upscope $end
$scope begin genblk1[7] $end
$var parameter 4 I i $end
$upscope $end
$upscope $end
$scope module cu $end
$var wire 1 J TYPE_ABS $end
$var wire 1 K TYPE_IMM $end
$var wire 1 L TYPE_OFF $end
$var wire 1 M TYPE_REG $end
$var wire 1 " clk $end
$var wire 8 N inst [7:0] $end
$var wire 4 O psr [3:0] $end
$var wire 1 # reset $end
$var wire 6 P opcode [5:0] $end
$var wire 16 Q decode [15:0] $end
$var wire 1 , cRI $end
$var wire 1 - cPS $end
$var wire 1 . cPI $end
$var wire 1 / cMI $end
$var wire 1 0 cLS $end
$var wire 4 R cL [3:0] $end
$var wire 1 2 cII $end
$var wire 1 3 cES $end
$var wire 1 4 cCn $end
$var wire 1 5 cAS $end
$var wire 1 6 cAI $end
$var parameter 32 S AI $end
$var parameter 33 T AS $end
$var parameter 14 U BUF_A $end
$var parameter 14 V BUF_B $end
$var parameter 39 W Cn $end
$var parameter 38 X ES $end
$var parameter 40 Y GEN_0 $end
$var parameter 40 Z GEN_1 $end
$var parameter 41 [ II $end
$var parameter 40 \ LS $end
$var parameter 36 ] MI $end
$var parameter 14 ^ NEG_A $end
$var parameter 14 _ NEG_B $end
$var parameter 34 ` PI $end
$var parameter 35 a PS $end
$var parameter 37 b RI $end
$var parameter 6 c add $end
$var parameter 6 d addc $end
$var parameter 6 e jump $end
$var parameter 6 f jumpc $end
$var parameter 6 g jumpn $end
$var parameter 6 h jumpz $end
$var parameter 6 i load $end
$var parameter 6 j loadi $end
$var parameter 6 k store $end
$var parameter 6 l sub $end
$var parameter 6 m subb $end
$var reg 3 n counter [2:0] $end
$upscope $end
$scope module ram $end
$var wire 1 / MI $end
$var wire 1 , RI $end
$var wire 1 " clk $end
$var wire 8 o display [7:0] $end
$var wire 8 p mar [7:0] $end
$var wire 8 q read [7:0] $end
$var wire 1 # reset $end
$var wire 8 r write [7:0] $end
$var parameter 32 s WIDTH $end
$var parameter 38 t abs $end
$var parameter 5 u adc $end
$var parameter 38 v adca $end
$var parameter 5 w add $end
$var parameter 38 x adda $end
$var parameter 32 y count $end
$var parameter 32 z first $end
$var parameter 38 { imm $end
$var parameter 38 | jump $end
$var parameter 38 } jumpc $end
$var parameter 38 ~ jumpn $end
$var parameter 38 !" jumpz $end
$var parameter 38 "" loada $end
$var parameter 5 #" loadi $end
$var parameter 38 $" off $end
$var parameter 5 %" sbb $end
$var parameter 38 &" sbba $end
$var parameter 32 '" second $end
$var parameter 38 (" store $end
$var parameter 5 )" sub $end
$var parameter 38 *" suba $end
$var parameter 32 +" tmp $end
$var reg 8 ," mem_addr_reg [7:0] $end
$var integer 32 -" finish [31:0] $end
$var integer 32 ." i [31:0] $end
$var integer 32 /" org [31:0] $end
$var integer 32 0" start [31:0] $end
$upscope $end
$scope module rega_mux $end
$var wire 1 " clk $end
$var wire 1 6 enable $end
$var wire 8 1" in0 [7:0] $end
$var wire 8 2" in1 [7:0] $end
$var wire 1 # reset $end
$var wire 1 5 sel $end
$var parameter 32 3" WIDTH $end
$var reg 8 4" out [7:0] $end
$upscope $end
$upscope $end
$upscope $end
$enddefinitions $end
$comment Show the parameter values. $end
$dumpall
b1000 3"
b1010 +"
b1001011 *"
b1011 )"
b1000010 ("
b1100 '"
b1001010 &"
b1010 %"
b10000000 $"
b1 #"
b1000001 ""
b1000101 !"
b1000111 ~
b1000110 }
b1000100 |
b0 {
b1011 z
b1101 y
b1001000 x
b1000 w
b1001001 v
b1001 u
b1000000 t
b1000 s
b1010 m
b1011 l
b10 k
b1 j
b1 i
b101 h
b111 g
b110 f
b100 e
b1001 d
b1000 c
b100000 b
b1000 a
b100 `
b1010000000000 _
b110000000000 ^
b10000 ]
b100000000 \
b1000000000 [
b11110100000000 Z
b100000000 Y
b1000000 X
b10000000 W
b10100000000000 V
b11000000000000 U
b10 T
b1 S
b111 I
b110 H
b101 G
b100 F
b11 E
b10 D
b1 C
b0 B
b1000 @
b1000 7
$end
#0
$dumpvars
b0 4"
b0 2"
b1100011 1"
b1100100 0"
b1111010 /"
b10000000 ."
b11001000 -"
b0 ,"
b0 r
b1100011 q
b0 p
b0 o
b0 n
b0 R
b100010000 Q
b0 P
bx O
b0 N
0M
0L
1K
0J
bx A
b0 ?
b1100011 >
b0 =
b0 <
b0 ;
b0 :
b0 9
b0 8
06
05
04
03
02
b0 1
10
1/
0.
0-
0,
b0 +
b0 *
b0 )
b100010000 (
b0 '
bx &
b1100011 %
b0 $
1#
0"
x!
$end
#1
0#
1"
#2
b1100011 :
b1100100 $
b1100100 r
b1100100 2"
b1100100 *
b1100100 =
b1100100 9
b1010 1
b1010 <
b1010 R
1,
14
b10100110110000 (
b10100110110000 Q
b1 )
b1 n
0"
#3
b1000010 $
b1000010 r
b1000010 2"
b1000010 *
b1000010 =
b1000010 9
b1000001 :
b1000001 %
b1000001 >
b1000001 q
b1000001 1"
b1100100 '
b1100100 p
b1100100 ,"
1"
#4
b0 :
b0 $
b0 r
b0 2"
b0 *
b0 =
b0 9
b0 1
b0 <
b0 R
0,
04
12
b1100010000 (
b1100010000 Q
b10 )
b10 n
0"
#5
0K
1J
b1 P
0!
b1000001 8
b1000001 N
b1100100 %
b1100100 >
b1100100 q
b1100100 1"
b0 '
b0 p
b0 ,"
1"
#6
b1100100 :
b1100101 $
b1100101 r
b1100101 2"
b1100101 *
b1100101 =
b1100101 9
b1010 1
b1010 <
b1010 R
1,
14
02
b10100110110000 (
b10100110110000 Q
b11 )
b11 n
0"
#7
b1110 $
b1110 r
b1110 2"
b1110 *
b1110 =
b1110 9
b1101 :
b1101 %
b1101 >
b1101 q
b1101 1"
b1100101 '
b1100101 p
b1100101 ,"
1"
#8
b1101 $
b1101 r
b1101 2"
b1101 *
b1101 =
b1101 9
0,
04
b10100100010000 (
b10100100010000 Q
b100 )
b100 n
0"
#9
b1110 $
b1110 r
b1110 2"
b1110 *
b1110 =
b1110 9
b1110 :
b1110 %
b1110 >
b1110 q
b1110 1"
b1101 '
b1101 p
b1101 ,"
1"
#10
b0 $
b0 r
b0 2"
b0 *
b0 =
b0 9
b0 :
b0 1
b0 <
b0 R
16
0/
00
b1 (
b1 Q
b101 )
b101 n
0"
#11
b1110 $
b1110 r
b1110 2"
b1110 *
b1110 =
b1110 9
b1110 ;
b1110 +
b1110 ?
b1110 4"
1"
#12
b0 $
b0 r
b0 2"
b0 *
b0 =
b0 9
b0 ;
1/
10
06
b100010000 (
b100010000 Q
b0 )
b0 n
0"
#13
b1100101 %
b1100101 >
b1100101 q
b1100101 1"
b0 '
b0 p
b0 ,"
1"
#14
b1100101 :
b1100110 $
b1100110 r
b1100110 2"
b1100110 *
b1100110 =
b1100110 9
b1010 1
b1010 <
b1010 R
1,
14
b10100110110000 (
b10100110110000 Q
b1 )
b1 n
0"
#15
b1011 $
b1011 r
b1011 2"
b1011 *
b1011 =
b1011 9
b1010 :
b1010 %
b1010 >
b1010 q
b1010 1"
b1100110 '
b1100110 p
b1100110 ,"
1"
#16
b0 :
b0 $
b0 r
b0 2"
b0 *
b0 =
b0 9
b0 1
b0 <
b0 R
0,
04
12
b1100010000 (
b1100010000 Q
b10 )
b10 n
0"
#17
1K
0J
b1010 P
b1010 8
b1010 N
b1100110 %
b1100110 >
b1100110 q
b1100110 1"
b0 '
b0 p
b0 ,"
1"
#18
b1100110 :
b1100111 $
b1100111 r
b1100111 2"
b1100111 *
b1100111 =
b1100111 9
b1010 1
b1010 <
b1010 R
1,
14
02
b10100110110000 (
b10100110110000 Q
b11 )
b11 n
0"
#19
b1 $
b1 r
b1 2"
b1 *
b1 =
b1 9
b0 :
b0 %
b0 >
b0 q
b0 1"
b1100111 '
b1100111 p
b1100111 ,"
1"
#20
b11111111 :
b1101 $
b1101 r
b1101 2"
b1101 *
b1101 =
b100001101 9
b1110 ;
b101 1
b101 <
b101 R
16
15
1.
0/
0,
04
00
b1010000000111 (
b1010000000111 Q
b100 )
b100 n
0"
#21
b1 &
b1 A
b1 O
b1100 $
b1100 r
b1100 2"
b1100 *
b1100 =
b100001100 9
b1101 ;
b1101 +
b1101 ?
b1101 4"
1"
#22
b0 ;
1/
10
b0 $
b0 r
b0 2"
b0 *
b0 =
b0 9
b0 :
b0 1
b0 <
b0 R
06
05
0.
b100010000 (
b100010000 Q
b0 )
b0 n
0"
#23
b1100111 %
b1100111 >
b1100111 q
b1100111 1"
b0 '
b0 p
b0 ,"
1"
#24
b1100111 :
b1101000 $
b1101000 r
b1101000 2"
b1101000 *
b1101000 =
b1101000 9
b1010 1
b1010 <
b1010 R
1,
14
b10100110110000 (
b10100110110000 Q
b1 )
b1 n
0"
#25
b1000011 $
b1000011 r
b1000011 2"
b1000011 *
b1000011 =
b1000011 9
b1000010 :
b1000010 %
b1000010 >
b1000010 q
b1000010 1"
b1101000 '
b1101000 p
b1101000 ,"
1"
#26
b0 :
b0 $
b0 r
b0 2"
b0 *
b0 =
b0 9
b0 1
b0 <
b0 R
0,
04
12
b1100010000 (
b1100010000 Q
b10 )
b10 n
0"
#27
0K
1J
b10 P
b1101000 %
b1101000 >
b1101000 q
b1101000 1"
b0 '
b0 p
b0 ,"
b1000010 8
b1000010 N
1"
#28
b1101000 :
b1101001 $
b1101001 r
b1101001 2"
b1101001 *
b1101001 =
b1101001 9
b1010 1
b1010 <
b1010 R
1,
14
02
b10100110110000 (
b10100110110000 Q
b11 )
b11 n
0"
#29
b1110 $
b1110 r
b1110 2"
b1110 *
b1110 =
b1110 9
b1101 :
b1101 %
b1101 >
b1101 q
b1101 1"
b1101001 '
b1101001 p
b1101001 ,"
1"
#30
b1101 $
b1101 r
b1101 2"
b1101 *
b1101 =
b1101 9
0,
04
b10100100010000 (
b10100100010000 Q
b100 )
b100 n
0"
#31
b1110 $
b1110 r
b1110 2"
b1110 *
b1110 =
b1110 9
b1110 :
b1110 %
b1110 >
b1110 q
b1110 1"
b1101 '
b1101 p
b1101 ,"
1"
#32
b1101 $
b1101 r
b1101 2"
b1101 *
b1101 =
b1101 9
b1101 :
b1100 1
b1100 <
b1100 R
0/
1,
b11000100100000 (
b11000100100000 Q
b101 )
b101 n
0"
#33
b1101 %
b1101 >
b1101 q
b1101 1"
1"
#34
1/
b0 :
b0 $
b0 r
b0 2"
b0 *
b0 =
b0 9
b0 ;
b0 1
b0 <
b0 R
0,
10
b100010000 (
b100010000 Q
b0 )
b0 n
0"
#35
b1101001 %
b1101001 >
b1101001 q
b1101001 1"
b0 '
b0 p
b0 ,"
1"
#36
b1101001 :
b1101010 $
b1101010 r
b1101010 2"
b1101010 *
b1101010 =
b1101010 9
b1010 1
b1010 <
b1010 R
1,
14
b10100110110000 (
b10100110110000 Q
b1 )
b1 n
0"
#37
b1000110 $
b1000110 r
b1000110 2"
b1000110 *
b1000110 =
b1000110 9
b1000101 :
b1000101 %
b1000101 >
b1000101 q
b1000101 1"
b1101010 '
b1101010 p
b1101010 ,"
1"
#38
b0 :
b0 $
b0 r
b0 2"
b0 *
b0 =
b0 9
b0 1
b0 <
b0 R
0,
04
12
b1100010000 (
b1100010000 Q
b10 )
b10 n
0"
#39
b101 P
b1101010 %
b1101010 >
b1101010 q
b1101010 1"
b0 '
b0 p
b0 ,"
b1000101 8
b1000101 N
1"
#40
b1101010 :
b1101011 $
b1101011 r
b1101011 2"
b1101011 *
b1101011 =
b1101011 9
b1010 1
b1010 <
b1010 R
1,
14
02
b10100110110000 (
b10100110110000 Q
b11 )
b11 n
0"
#41
b11001000 $
b11001000 r
b11001000 2"
b11001000 *
b11001000 =
b11001000 9
b11000111 :
b11000111 %
b11000111 >
b11000111 q
b11000111 1"
b1101011 '
b1101011 p
b1101011 ,"
1"
#42
b0 :
b0 $
b0 r
b0 2"
b0 *
b0 =
b0 9
b0 ;
b0 1
b0 <
b0 R
1/
0,
04
10
b100010000 (
b100010000 Q
b0 )
b0 n
0"
#43
b1101011 %
b1101011 >
b1101011 q
b1101011 1"
b0 '
b0 p
b0 ,"
1"
#44
b1101011 :
b1101100 $
b1101100 r
b1101100 2"
b1101100 *
b1101100 =
b1101100 9
b1010 1
b1010 <
b1010 R
1,
14
b10100110110000 (
b10100110110000 Q
b1 )
b1 n
0"
#45
b1000010 $
b1000010 r
b1000010 2"
b1000010 *
b1000010 =
b1000010 9
b1000001 :
b1000001 %
b1000001 >
b1000001 q
b1000001 1"
b1101100 '
b1101100 p
b1101100 ,"
1"
#46
b0 :
b0 $
b0 r
b0 2"
b0 *
b0 =
b0 9
b0 1
b0 <
b0 R
0,
04
12
b1100010000 (
b1100010000 Q
b10 )
b10 n
0"
#47
b1 P
b1101100 %
b1101100 >
b1101100 q
b1101100 1"
b0 '
b0 p
b0 ,"
b1000001 8
b1000001 N
1"
#48
b1101100 :
b1101101 $
b1101101 r
b1101101 2"
b1101101 *
b1101101 =
b1101101 9
b1010 1
b1010 <
b1010 R
1,
14
02
b10100110110000 (
b10100110110000 Q
b11 )
b11 n
0"
#49
b1101 $
b1101 r
b1101 2"
b1101 *
b1101 =
b1101 9
b1100 :
b1100 %
b1100 >
b1100 q
b1100 1"
b1101101 '
b1101101 p
b1101101 ,"
1"
#50
b1100 $
b1100 r
b1100 2"
b1100 *
b1100 =
b1100 9
0,
04
b10100100010000 (
b10100100010000 Q
b100 )
b100 n
0"
#51
b1 $
b1 r
b1 2"
b1 *
b1 =
b1 9
b1 :
b1 %
b1 >
b1 q
b1 1"
b1100 '
b1100 p
b1100 ,"
1"
#52
b0 :
b1101 $
b1101 r
b1101 2"
b1101 *
b1101 =
b1101 9
b1101 ;
b0 1
b0 <
b0 R
16
0/
00
b1 (
b1 Q
b101 )
b101 n
0"
#53
b1 $
b1 r
b1 2"
b1 *
b1 =
b1 9
b1 ;
b1 +
b1 ?
b1 4"
1"
#54
b0 $
b0 r
b0 2"
b0 *
b0 =
b0 9
b0 ;
1/
10
06
b100010000 (
b100010000 Q
b0 )
b0 n
0"
#55
b1101101 %
b1101101 >
b1101101 q
b1101101 1"
b0 '
b0 p
b0 ,"
1"
#56
b1101101 :
b1101110 $
b1101110 r
b1101110 2"
b1101110 *
b1101110 =
b1101110 9
b1010 1
b1010 <
b1010 R
1,
14
b10100110110000 (
b10100110110000 Q
b1 )
b1 n
0"
#57
b1000011 $
b1000011 r
b1000011 2"
b1000011 *
b1000011 =
b1000011 9
b1000010 :
b1000010 %
b1000010 >
b1000010 q
b1000010 1"
b1101110 '
b1101110 p
b1101110 ,"
1"
#58
b0 :
b0 $
b0 r
b0 2"
b0 *
b0 =
b0 9
b0 1
b0 <
b0 R
0,
04
12
b1100010000 (
b1100010000 Q
b10 )
b10 n
0"
#59
b10 P
b1101110 %
b1101110 >
b1101110 q
b1101110 1"
b0 '
b0 p
b0 ,"
b1000010 8
b1000010 N
1"
#60
b1101110 :
b1101111 $
b1101111 r
b1101111 2"
b1101111 *
b1101111 =
b1101111 9
b1010 1
b1010 <
b1010 R
1,
14
02
b10100110110000 (
b10100110110000 Q
b11 )
b11 n
0"
#61
b1011 $
b1011 r
b1011 2"
b1011 *
b1011 =
b1011 9
b1010 :
b1010 %
b1010 >
b1010 q
b1010 1"
b1101111 '
b1101111 p
b1101111 ,"
1"
#62
b1010 $
b1010 r
b1010 2"
b1010 *
b1010 =
b1010 9
0,
04
b10100100010000 (
b10100100010000 Q
b100 )
b100 n
0"
#63
b0 $
b0 r
b0 2"
b0 *
b0 =
b0 9
b0 :
b0 %
b0 >
b0 q
b0 1"
b1010 '
b1010 p
b1010 ,"
1"
#64
b1 $
b1 r
b1 2"
b1 *
b1 =
b1 9
b1 :
b1100 1
b1100 <
b1100 R
0/
1,
b11000100100000 (
b11000100100000 Q
b101 )
b101 n
0"
#65
b1 %
b1 >
b1 q
b1 1"
1"
#66
1/
b0 :
b0 $
b0 r
b0 2"
b0 *
b0 =
b0 9
b0 ;
b0 1
b0 <
b0 R
0,
10
b100010000 (
b100010000 Q
b0 )
b0 n
0"
#67
b1101111 %
b1101111 >
b1101111 q
b1101111 1"
b0 '
b0 p
b0 ,"
1"
#68
b1101111 :
b1110000 $
b1110000 r
b1110000 2"
b1110000 *
b1110000 =
b1110000 9
b1010 1
b1010 <
b1010 R
1,
14
b10100110110000 (
b10100110110000 Q
b1 )
b1 n
0"
#69
b1001001 $
b1001001 r
b1001001 2"
b1001001 *
b1001001 =
b1001001 9
b1001000 :
b1001000 %
b1001000 >
b1001000 q
b1001000 1"
b1110000 '
b1110000 p
b1110000 ,"
1"
#70
b0 :
b0 $
b0 r
b0 2"
b0 *
b0 =
b0 9
b0 1
b0 <
b0 R
0,
04
12
b1100010000 (
b1100010000 Q
b10 )
b10 n
0"
#71
b1000 P
b1110000 %
b1110000 >
b1110000 q
b1110000 1"
b0 '
b0 p
b0 ,"
b1001000 8
b1001000 N
1"
#72
b1110000 :
b1110001 $
b1110001 r
b1110001 2"
b1110001 *
b1110001 =
b1110001 9
b1010 1
b1010 <
b1010 R
1,
14
02
b10100110110000 (
b10100110110000 Q
b11 )
b11 n
0"
#73
b1100 $
b1100 r
b1100 2"
b1100 *
b1100 =
b1100 9
b1011 :
b1011 %
b1011 >
b1011 q
b1011 1"
b1110001 '
b1110001 p
b1110001 ,"
1"
#74
b1011 $
b1011 r
b1011 2"
b1011 *
b1011 =
b1011 9
0,
04
b10100100010000 (
b10100100010000 Q
b100 )
b100 n
0"
#75
b0 $
b0 r
b0 2"
b0 *
b0 =
b0 9
b0 :
b0 %
b0 >
b0 q
b0 1"
b1011 '
b1011 p
b1011 ,"
1"
#76
b1 $
b1 r
b1 2"
b1 *
b1 =
b1 9
b1 ;
16
15
1.
0/
00
b10100000000111 (
b10100000000111 Q
b101 )
b101 n
0"
#77
b0 &
b0 A
b0 O
1"
#78
b0 $
b0 r
b0 2"
b0 *
b0 =
b0 9
b0 ;
1/
10
b0 1
b0 <
b0 R
06
05
0.
b100010000 (
b100010000 Q
b0 )
b0 n
0"
#79
b1110001 %
b1110001 >
b1110001 q
b1110001 1"
b0 '
b0 p
b0 ,"
1"
