tiny.sv


module alu16 #(parameter WIDTH = 16) (clk, reset, A, B, E, L, LS, Cn, PI, PS, psr);
    input [WIDTH - 1:0] A, B;
    input [3:0] L;
    input Cn;
    input clk;
    input reset;
	input LS;
    input PI, PS;

    output [WIDTH - 1:0] E;
    output reg [3:0] psr;

    wire [WIDTH - 1:0] lA;
    wire [WIDTH - 1:0] lB;
    wire [WIDTH:0] tE;

	genvar i;

	for (i = 0; i < WIDTH; i = i + 1)
		assign lB[i] = A[i] ? (B[i] ? L[3] : L[2]) : (B[i] ? L[1] : L[0]);

	assign lA = LS ? 0: A;
    assign tE = { 1'b0, lA } + { 1'b0, lB } + (1 & Cn);
    assign E = tE[WIDTH - 1:0];

	// assign psr_wire[3] = (E[WIDTH - 1] & ~A[WIDTH - 1] & (lB[WIDTH - 1] == 0)) | (~E[WIDTH - 1] & A[WIDTH - 1] & lB[WIDTH - 1]);

    always @(posedge clk or negedge reset) begin
        if (reset == 1) begin
            psr <= 0;
        end
        else
        if (PI == 1) begin
			psr[0] <= tE[WIDTH];
			psr[1] <= E[WIDTH - 1];
			psr[2] <= (E[WIDTH - 1: 0] == 0) ? 1: 0;
			psr[3] <= 0;

            // if (PS == 1) begin
            // end
            // else begin
            //     psr <= psr_wire;
            // end
        end
    end
endmodule


module sync_mux_2x1 #(parameter WIDTH = 16) (clk, reset, sel, enable, in0, in1, out);
    input sel, enable, clk, reset;
    input [WIDTH - 1:0] in0, in1;

    output reg [WIDTH - 1:0] out;

    always @(posedge clk or posedge reset) begin
        if (reset == 1)
            out = 0;
        else
        if (enable) begin
            if (sel == 1)
                out = in1;
            else
                out = in0;
        end
    end
endmodule


module memory #(parameter WIDTH = 16) (clk, reset, MI, RI, write, read, mar);
    input clk, MI, RI;
    input reset;
    
    output [WIDTH - 1:0] mar;
    input [WIDTH - 1:0] write;
    output [WIDTH - 1:0] read;
    
    reg [WIDTH - 1:0] mem_addr_reg;
    reg [WIDTH - 1:0] ram [2**16-1:0];
    
    integer i;

    assign mar = mem_addr_reg;
	
	// assign TYPE_IMM = ~inst[7] & ~inst[6];	// 0
	// assign TYPE_ABS = ~inst[7] & inst[6];	// 1
	// assign TYPE_OFF = inst[7] & ~inst[6];	// 2
	// assign TYPE_REG = inst[7] & inst[6];	// 3
	
	parameter imm = 0 << 6;
	parameter abs = 1 << 6;
	parameter off = 2 << 6;

	parameter loadi	= 	5'b00001;
	parameter loada =	loadi | abs;

	parameter store = 	5'b00010 | abs;

	parameter jump 	= 	5'b00100 | abs;
	parameter jumpz =	5'b00101 | abs;
	parameter jumpc =	5'b00110 | abs;
	parameter jumpn =	5'b00111 | abs;

	parameter add 	= 	5'b01000;
	parameter adc 	= 	5'b01001;
	parameter sbb 	= 	5'b01010;
	parameter sub 	= 	5'b01011;
	
	parameter adda 	= 	add | abs;
	parameter adca 	= 	adc | abs;
	parameter sbba 	= 	sbb | abs;
	parameter suba 	= 	sub | abs;
		
	parameter tmp = 10;
	parameter first = 11;
	parameter second = 12;
	parameter count = 13;

	integer org, start, finish;

    always @(posedge clk or posedge reset) begin
        if (reset == 1) begin
            mem_addr_reg <= 0;

            for (i = 0; i < 2**(WIDTH - 1); i++)
                ram[i] = 0;
			
			org = 100;

			ram[0] = org - 1;

			ram[first] = 0;
			ram[second] = 1;
			ram[count] = 9;

			start = org++;
			ram[start] = loada; ram[org++] = count;
			ram[org++] = sub; ram[org++] = 10;
			ram[org++] = sub; ram[org++] = 10;
			ram[org++] = sub; ram[org++] = 10;
			ram[org++] = sub; ram[org++] = 10;
			ram[org++] = store; ram[org++] = count;
			ram[org++] = suba; ram[org++] = count;
			ram[org++] = jumpz; ram[org++] = start - 1;

			finish = org++;
			ram[finish] = 8'hff;
			ram[org++] = 4;
        end else begin
            if (MI == 1)
                mem_addr_reg <= write;

            if (RI == 1)
                ram[mem_addr_reg] <= write;
        end
    end

    assign read = ram[mem_addr_reg];
endmodule


module controlunit(clk, reset, inst, psr, cAI, cAS, cPI, cPS, cMI, cRI, cES, cCn, cL, cLS, cII, decode, counter);
	// Enable Control Lines

    parameter AI = 1 << 0;
    parameter AS = 1 << 1;
    parameter PI = 1 << 2;
    parameter PS = 1 << 3;
    parameter MI = 1 << 4;
    parameter RI = 1 << 5;
    parameter ES = 1 << 6;
    parameter Cn = 1 << 7;
    parameter LS = 1 << 8;
    parameter II = 1 << 9;

	// ALU Control Liines

    parameter GEN_0 = 14'b0000_0000000000 | LS;
    parameter GEN_1 = 14'b1111_0000000000 | LS;
    parameter BUF_A = 14'b1100_0000000000;
    parameter NEG_A = 14'b0011_0000000000;
    parameter BUF_B = 14'b1010_0000000000;
    parameter NEG_B = 14'b0101_0000000000;

	parameter load 	= 	6'b000001;
	parameter loadi 	= 	6'b000001;

	parameter store = 	6'b000010;

	parameter jump 	= 	6'b000100;
	parameter jumpz =	6'b000101;
	parameter jumpc =	6'b000110;
	parameter jumpn =	6'b000111;

	parameter add 	= 	6'b001000;
	parameter addc 	= 	6'b001001;
	parameter subb 	= 	6'b001010;
	parameter sub 	= 	6'b001011;

	input clk;
    input reset;
    input [7:0] inst;
    input [3:0] psr;

    output wire cAI, cAS;
    output wire cPI, cPS;
    output wire cMI, cRI;
    output wire cES;
    output wire cCn;
    output wire cLS;
    output wire cII;
    output wire [3:0] cL;

    output [15:0] decode;
    output reg [2:0] counter;

	wire TYPE_REG, TYPE_IMM, TYPE_ABS, TYPE_OFF;
	wire [5:0] opcode;

	reg reset_counter;

	assign TYPE_IMM = ~inst[7] & ~inst[6];	// 0
	assign TYPE_ABS = ~inst[7] & inst[6];	// 1
	assign TYPE_OFF = inst[7] & ~inst[6];	// 2
	assign TYPE_REG = inst[7] & inst[6];	// 3

	assign opcode = inst[5:0];

    always @(negedge clk or posedge reset) begin
        if (reset == 1) begin
            counter <= 0;
        end else begin
			counter <= counter + 1;
        end
    end
	
	assign decode =
		counter == 0 ? GEN_0 | MI:
		counter == 1 ? BUF_B | Cn | MI | RI | LS:
		counter == 2 ? II | GEN_0 | MI:
		counter == 3 ? BUF_B | Cn | MI | RI | LS:
		counter == 4 ?
			TYPE_IMM ?
				opcode == load ? AI:

				opcode == add ? BUF_B | PI | AS | AI:
				opcode == addc ? BUF_B | PI | AS | AI | Cn:
				opcode == subb ? NEG_B | PI | AS | AI:
				opcode == sub ? NEG_B | PI | AS | AI | Cn:
				0:
			TYPE_ABS ?
				opcode == load ? BUF_B | MI | LS:

				opcode == store ? BUF_B | MI | LS:

				((opcode == jump) | ((opcode == jumpz) & (psr[2] == 1))) ? GEN_0 | MI | AI:

				opcode == add ? BUF_B | MI | LS:
				opcode == addc ? BUF_B | MI | LS:
				opcode == sub ? BUF_B | MI | LS:
				opcode == subb ? BUF_B | MI | LS:
				0:
			0:
		counter == 5 ?
			TYPE_ABS ?
				opcode == load ? AI:

				opcode == store ? BUF_A | RI | LS:

				((opcode == jump) | ((opcode == jumpz) & (psr[2] == 1))) ? BUF_A | MI | RI | LS:
				
				opcode == add ? BUF_B | PI | AS | AI:
				opcode == addc ? BUF_B | PI | AS | AI | Cn:
				opcode == subb ? NEG_B | PI | AS | AI:
				opcode == sub ? NEG_B | PI | AS | AI | Cn:
				0:
			0:
		0;

    assign cAI = decode[0];
    assign cAS = decode[1];
    assign cPI = decode[2];
    assign cPS = decode[3];
    assign cMI = decode[4];
    assign cRI = decode[5];
    assign cES = decode[6];
    assign cCn = decode[7];
    assign cLS = decode[8];
	assign cII = decode[9];
    assign cL = decode[14:10];
endmodule


module testbench;
	parameter WIDTH = 8;

    wire [WIDTH - 1:0] mem_input_bus;
    wire [WIDTH - 1:0] accumulator_bus;
    wire [WIDTH - 1:0] ram_read_bus;
    wire [WIDTH - 1:0] ram_write_bus;
    wire [WIDTH - 1:0] alu_out_bus;
    wire [3:0] psr_bus;

    reg clk;
    reg reset;
    reg [7:0] inst;

    wire AI, AS;
    wire PI, PS;
    wire MI, RI;
    wire ES;
    wire C_in;
	wire LS;
	wire II;
    wire [3:0] L;

    alu16 #(WIDTH) alu (clk, reset, accumulator_bus, ram_read_bus, alu_out_bus, L, LS, C_in, PI, PS, psr_bus);

    // ES == 0 -> ALU
    // ES == 1 -> PSR
    assign ram_write_bus = ES ? psr_bus: alu_out_bus;

    sync_mux_2x1 #(WIDTH) rega_mux(clk, reset, AS, AI, ram_read_bus, ram_write_bus, accumulator_bus);
    
    wire [WIDTH - 1:0] mar;
    memory #(WIDTH) ram(clk, reset, MI, RI, ram_write_bus, ram_read_bus, mar);

    wire [15:0] decode;
	wire [2:0] counter;
    controlunit cu(clk, reset, inst, psr_bus, AI, AS, PI, PS, MI, RI, ES, C_in, L, LS, II, decode, counter);

	always @(posedge clk or negedge reset) begin
		if (reset == 1)
			inst <= 0;
		else if (II == 1)
			inst <= ram_read_bus;
	end

    always @(posedge reset) begin
        inst <= 0;
    end
	
    initial begin
		inst = 0;
        clk = 0;
        reset = 1;
		
        while (~inst) begin
            #10 clk = ~clk;
            if (reset == 1 & clk)
                reset = 0;
        end
    end

    initial begin
        $dumpfile ("testbench.vcd");
        $dumpvars (0, testbench);
        $monitor ($time, ":\tclk=%B | reset=%B | step=%D | RAM_WRITE=%B:%D | RAM_READ=%B:%D | MAR=%B:%D | REG=%B:%D | psr=%B | decode=%B | Inst=%B", clk, reset, counter, ram_write_bus, ram_write_bus, ram_read_bus, ram_read_bus, mar, mar, accumulator_bus, accumulator_bus, psr_bus, decode, inst);
        // $monitor ($time, ":\tclk=%B | A=%B | B=%B | C=%B", clk, a, b, c);
        // #10 MI = 1; RI = 0; ram_write_bus = 1;
        // #20 MI = 1; RI = 0; ram_write_bus = 2;
        // #20 MI = 0; RI = 1; ram_write_bus = 3;
        // #20 MI = 1; ram_write_bus = 10;
        // #20 RI = 1; ram_write_bus = 1;
        // #20 MI = 1; ram_write_bus = 2;

        // #5 s = 1; a = 100; b = 0; e = 1;
        // #5 s = 0; b = 20;
        // #5 s = 1; b = 1;
        // #5 s = 1; b = 2;
        // #5 s = 1; b = 3;
        
        // ram_read_bus = 0; ram

        // #5 B = 8'd255; A = 0; L = 15;
        // #5 A = 10; B = 0; L = 4'b1100;	// Buff A
        // #5 A = 10; B = 0; L = 4'b0011;	// Neg A
        // #5 A = 10; B = 0; L = 4'b1010;	// Buff B
        // #5 A = 10; B = 0; L = 4'b0101;	// Neg B

        #2000
        $finish;
    end
endmodule

testbench.vcd
$date
	Sun Nov 26 21:45:20 2023
$end
$version
	Icarus Verilog
$end
$timescale
	1s
$end
$scope module testbench $end
$var wire 8 ! ram_write_bus [7:0] $end
$var wire 8 " ram_read_bus [7:0] $end
$var wire 4 # psr_bus [3:0] $end
$var wire 8 $ mar [7:0] $end
$var wire 16 % decode [15:0] $end
$var wire 3 & counter [2:0] $end
$var wire 8 ' alu_out_bus [7:0] $end
$var wire 8 ( accumulator_bus [7:0] $end
$var wire 1 ) RI $end
$var wire 1 * PS $end
$var wire 1 + PI $end
$var wire 1 , MI $end
$var wire 1 - LS $end
$var wire 4 . L [3:0] $end
$var wire 1 / II $end
$var wire 1 0 ES $end
$var wire 1 1 C_in $end
$var wire 1 2 AS $end
$var wire 1 3 AI $end
$var parameter 32 4 WIDTH $end
$var reg 1 5 clk $end
$var reg 8 6 inst [7:0] $end
$var reg 1 7 reset $end
$scope module alu $end
$var wire 1 5 clk $end
$var wire 1 7 reset $end
$var wire 9 8 tE [8:0] $end
$var wire 8 9 lB [7:0] $end
$var wire 8 : lA [7:0] $end
$var wire 1 * PS $end
$var wire 1 + PI $end
$var wire 1 - LS $end
$var wire 4 ; L [3:0] $end
$var wire 8 < E [7:0] $end
$var wire 1 1 Cn $end
$var wire 8 = B [7:0] $end
$var wire 8 > A [7:0] $end
$var parameter 32 ? WIDTH $end
$var reg 4 @ psr [3:0] $end
$scope begin genblk1[0] $end
$var parameter 2 A i $end
$upscope $end
$scope begin genblk1[1] $end
$var parameter 2 B i $end
$upscope $end
$scope begin genblk1[2] $end
$var parameter 3 C i $end
$upscope $end
$scope begin genblk1[3] $end
$var parameter 3 D i $end
$upscope $end
$scope begin genblk1[4] $end
$var parameter 4 E i $end
$upscope $end
$scope begin genblk1[5] $end
$var parameter 4 F i $end
$upscope $end
$scope begin genblk1[6] $end
$var parameter 4 G i $end
$upscope $end
$scope begin genblk1[7] $end
$var parameter 4 H i $end
$upscope $end
$upscope $end
$scope module cu $end
$var wire 1 I TYPE_ABS $end
$var wire 1 J TYPE_IMM $end
$var wire 1 K TYPE_OFF $end
$var wire 1 L TYPE_REG $end
$var wire 1 5 clk $end
$var wire 8 M inst [7:0] $end
$var wire 4 N psr [3:0] $end
$var wire 1 7 reset $end
$var wire 6 O opcode [5:0] $end
$var wire 16 P decode [15:0] $end
$var wire 1 ) cRI $end
$var wire 1 * cPS $end
$var wire 1 + cPI $end
$var wire 1 , cMI $end
$var wire 1 - cLS $end
$var wire 4 Q cL [3:0] $end
$var wire 1 / cII $end
$var wire 1 0 cES $end
$var wire 1 1 cCn $end
$var wire 1 2 cAS $end
$var wire 1 3 cAI $end
$var parameter 32 R AI $end
$var parameter 33 S AS $end
$var parameter 14 T BUF_A $end
$var parameter 14 U BUF_B $end
$var parameter 39 V Cn $end
$var parameter 38 W ES $end
$var parameter 40 X GEN_0 $end
$var parameter 40 Y GEN_1 $end
$var parameter 41 Z II $end
$var parameter 40 [ LS $end
$var parameter 36 \ MI $end
$var parameter 14 ] NEG_A $end
$var parameter 14 ^ NEG_B $end
$var parameter 34 _ PI $end
$var parameter 35 ` PS $end
$var parameter 37 a RI $end
$var parameter 6 b add $end
$var parameter 6 c addc $end
$var parameter 6 d jump $end
$var parameter 6 e jumpc $end
$var parameter 6 f jumpn $end
$var parameter 6 g jumpz $end
$var parameter 6 h load $end
$var parameter 6 i loadi $end
$var parameter 6 j store $end
$var parameter 6 k sub $end
$var parameter 6 l subb $end
$var reg 3 m counter [2:0] $end
$upscope $end
$scope module ram $end
$var wire 1 , MI $end
$var wire 1 ) RI $end
$var wire 1 5 clk $end
$var wire 8 n mar [7:0] $end
$var wire 8 o read [7:0] $end
$var wire 1 7 reset $end
$var wire 8 p write [7:0] $end
$var parameter 32 q WIDTH $end
$var parameter 38 r abs $end
$var parameter 5 s adc $end
$var parameter 38 t adca $end
$var parameter 5 u add $end
$var parameter 38 v adda $end
$var parameter 32 w count $end
$var parameter 32 x first $end
$var parameter 38 y imm $end
$var parameter 38 z jump $end
$var parameter 38 { jumpc $end
$var parameter 38 | jumpn $end
$var parameter 38 } jumpz $end
$var parameter 38 ~ loada $end
$var parameter 5 !" loadi $end
$var parameter 38 "" off $end
$var parameter 5 #" sbb $end
$var parameter 38 $" sbba $end
$var parameter 32 %" second $end
$var parameter 38 &" store $end
$var parameter 5 '" sub $end
$var parameter 38 (" suba $end
$var parameter 32 )" tmp $end
$var reg 8 *" mem_addr_reg [7:0] $end
$var integer 32 +" finish [31:0] $end
$var integer 32 ," i [31:0] $end
$var integer 32 -" org [31:0] $end
$var integer 32 ." start [31:0] $end
$upscope $end
$scope module rega_mux $end
$var wire 1 5 clk $end
$var wire 1 3 enable $end
$var wire 8 /" in0 [7:0] $end
$var wire 8 0" in1 [7:0] $end
$var wire 1 7 reset $end
$var wire 1 2 sel $end
$var parameter 32 1" WIDTH $end
$var reg 8 2" out [7:0] $end
$upscope $end
$upscope $end
$enddefinitions $end
$comment Show the parameter values. $end
$dumpall
b1000 1"
b1010 )"
b1001011 ("
b1011 '"
b1000010 &"
b1100 %"
b1001010 $"
b1010 #"
b10000000 ""
b1 !"
b1000001 ~
b1000101 }
b1000111 |
b1000110 {
b1000100 z
b0 y
b1011 x
b1101 w
b1001000 v
b1000 u
b1001001 t
b1001 s
b1000000 r
b1000 q
b1010 l
b1011 k
b10 j
b1 i
b1 h
b101 g
b111 f
b110 e
b100 d
b1001 c
b1000 b
b100000 a
b1000 `
b100 _
b1010000000000 ^
b110000000000 ]
b10000 \
b100000000 [
b1000000000 Z
b11110100000000 Y
b100000000 X
b1000000 W
b10000000 V
b10100000000000 U
b11000000000000 T
b10 S
b1 R
b111 H
b110 G
b101 F
b100 E
b11 D
b10 C
b1 B
b0 A
b1000 ?
b1000 4
$end
#0
$dumpvars
b0 2"
b0 0"
b1100011 /"
b1100100 ."
b1110110 -"
b10000000 ,"
b1110100 +"
b0 *"
b0 p
b1100011 o
b0 n
b0 m
b0 Q
b100010000 P
b0 O
bx N
b0 M
0L
0K
1J
0I
bx @
b0 >
b1100011 =
b0 <
b0 ;
b0 :
b0 9
b0 8
17
b0 6
05
03
02
01
00
0/
b0 .
1-
1,
0+
0*
0)
b0 (
b0 '
b0 &
b100010000 %
b0 $
bx #
b1100011 "
b0 !
$end
#10
07
15
#20
b1100011 9
b1100100 !
b1100100 p
b1100100 0"
b1100100 '
b1100100 <
b1100100 8
b1010 .
b1010 ;
b1010 Q
1)
11
b10100110110000 %
b10100110110000 P
b1 &
b1 m
05
#30
b1000010 !
b1000010 p
b1000010 0"
b1000010 '
b1000010 <
b1000010 8
b1000001 9
b1000001 "
b1000001 =
b1000001 o
b1000001 /"
b1100100 $
b1100100 n
b1100100 *"
15
#40
b0 9
b0 !
b0 p
b0 0"
b0 '
b0 <
b0 8
b0 .
b0 ;
b0 Q
0)
01
1/
b1100010000 %
b1100010000 P
b10 &
b10 m
05
#50
0J
1I
b1 O
b1000001 6
b1000001 M
b1100100 "
b1100100 =
b1100100 o
b1100100 /"
b0 $
b0 n
b0 *"
15
#60
b1100100 9
b1100101 !
b1100101 p
b1100101 0"
b1100101 '
b1100101 <
b1100101 8
b1010 .
b1010 ;
b1010 Q
1)
11
0/
b10100110110000 %
b10100110110000 P
b11 &
b11 m
05
#70
b1110 !
b1110 p
b1110 0"
b1110 '
b1110 <
b1110 8
b1101 9
b1101 "
b1101 =
b1101 o
b1101 /"
b1100101 $
b1100101 n
b1100101 *"
15
#80
b1101 !
b1101 p
b1101 0"
b1101 '
b1101 <
b1101 8
0)
01
b10100100010000 %
b10100100010000 P
b100 &
b100 m
05
#90
b1001 !
b1001 p
b1001 0"
b1001 '
b1001 <
b1001 8
b1001 9
b1001 "
b1001 =
b1001 o
b1001 /"
b1101 $
b1101 n
b1101 *"
15
#100
b0 !
b0 p
b0 0"
b0 '
b0 <
b0 8
b0 9
b0 .
b0 ;
b0 Q
13
0,
0-
b1 %
b1 P
b101 &
b101 m
05
#110
b1001 !
b1001 p
b1001 0"
b1001 '
b1001 <
b1001 8
b1001 :
b1001 (
b1001 >
b1001 2"
15
#120
03
b0 %
b0 P
b110 &
b110 m
05
#130
15
#140
b111 &
b111 m
05
#150
15
#160
b0 !
b0 p
b0 0"
b0 '
b0 <
b0 8
b0 :
1,
1-
b100010000 %
b100010000 P
b0 &
b0 m
05
#170
b1100101 "
b1100101 =
b1100101 o
b1100101 /"
b0 $
b0 n
b0 *"
15
#180
b1100101 9
b1100110 !
b1100110 p
b1100110 0"
b1100110 '
b1100110 <
b1100110 8
b1010 .
b1010 ;
b1010 Q
1)
11
b10100110110000 %
b10100110110000 P
b1 &
b1 m
05
#190
b1100 !
b1100 p
b1100 0"
b1100 '
b1100 <
b1100 8
b1011 9
b1011 "
b1011 =
b1011 o
b1011 /"
b1100110 $
b1100110 n
b1100110 *"
15
#200
b0 9
b0 !
b0 p
b0 0"
b0 '
b0 <
b0 8
b0 .
b0 ;
b0 Q
0)
01
1/
b1100010000 %
b1100010000 P
b10 &
b10 m
05
#210
1J
0I
b1011 O
b1011 6
b1011 M
b1100110 "
b1100110 =
b1100110 o
b1100110 /"
b0 $
b0 n
b0 *"
15
#220
b1100110 9
b1100111 !
b1100111 p
b1100111 0"
b1100111 '
b1100111 <
b1100111 8
b1010 .
b1010 ;
b1010 Q
1)
11
0/
b10100110110000 %
b10100110110000 P
b11 &
b11 m
05
#230
b1011 !
b1011 p
b1011 0"
b1011 '
b1011 <
b1011 8
b1010 9
b1010 "
b1010 =
b1010 o
b1010 /"
b1100111 $
b1100111 n
b1100111 *"
15
#240
b11110101 9
b11111111 !
b11111111 p
b11111111 0"
b11111111 '
b11111111 <
b11111111 8
b1001 :
b101 .
b101 ;
b101 Q
13
12
1+
0,
0)
0-
b1010010000111 %
b1010010000111 P
b100 &
b100 m
05
#250
b10 #
b10 @
b10 N
b11110101 !
b11110101 p
b11110101 0"
b11110101 '
b11110101 <
b111110101 8
b11111111 :
b11111111 (
b11111111 >
b11111111 2"
15
#260
b0 9
b11111111 !
b11111111 p
b11111111 0"
b11111111 '
b11111111 <
b11111111 8
b0 .
b0 ;
b0 Q
03
02
0+
01
b0 %
b0 P
b101 &
b101 m
05
#270
15
#280
b110 &
b110 m
05
#290
15
#300
b111 &
b111 m
05
#310
15
#320
b0 !
b0 p
b0 0"
b0 '
b0 <
b0 8
b0 :
1,
1-
b100010000 %
b100010000 P
b0 &
b0 m
05
#330
b1100111 "
b1100111 =
b1100111 o
b1100111 /"
b0 $
b0 n
b0 *"
15
#340
b1100111 9
b1101000 !
b1101000 p
b1101000 0"
b1101000 '
b1101000 <
b1101000 8
b1010 .
b1010 ;
b1010 Q
1)
11
b10100110110000 %
b10100110110000 P
b1 &
b1 m
05
#350
b1100 !
b1100 p
b1100 0"
b1100 '
b1100 <
b1100 8
b1011 9
b1011 "
b1011 =
b1011 o
b1011 /"
b1101000 $
b1101000 n
b1101000 *"
15
#360
b0 9
b0 !
b0 p
b0 0"
b0 '
b0 <
b0 8
b0 .
b0 ;
b0 Q
0)
01
1/
b1100010000 %
b1100010000 P
b10 &
b10 m
05
#370
b1101000 "
b1101000 =
b1101000 o
b1101000 /"
b0 $
b0 n
b0 *"
15
#380
b1101000 9
b1101001 !
b1101001 p
b1101001 0"
b1101001 '
b1101001 <
b1101001 8
b1010 .
b1010 ;
b1010 Q
1)
11
0/
b10100110110000 %
b10100110110000 P
b11 &
b11 m
05
#390
b1011 !
b1011 p
b1011 0"
b1011 '
b1011 <
b1011 8
b1010 9
b1010 "
b1010 =
b1010 o
b1010 /"
b1101001 $
b1101001 n
b1101001 *"
15
#400
b11110101 9
b11110101 !
b11110101 p
b11110101 0"
b11110101 '
b11110101 <
b111110101 8
b11111111 :
b101 .
b101 ;
b101 Q
13
12
1+
0,
0)
0-
b1010010000111 %
b1010010000111 P
b100 &
b100 m
05
#410
b11 #
b11 @
b11 N
b11101011 !
b11101011 p
b11101011 0"
b11101011 '
b11101011 <
b111101011 8
b11110101 :
b11110101 (
b11110101 >
b11110101 2"
15
#420
b0 9
b11110101 !
b11110101 p
b11110101 0"
b11110101 '
b11110101 <
b11110101 8
b0 .
b0 ;
b0 Q
03
02
0+
01
b0 %
b0 P
b101 &
b101 m
05
#430
15
#440
b110 &
b110 m
05
#450
15
#460
b111 &
b111 m
05
#470
15
#480
b0 !
b0 p
b0 0"
b0 '
b0 <
b0 8
b0 :
1,
1-
b100010000 %
b100010000 P
b0 &
b0 m
05
#490
b1101001 "
b1101001 =
b1101001 o
b1101001 /"
b0 $
b0 n
b0 *"
15
#500
b1101001 9
b1101010 !
b1101010 p
b1101010 0"
b1101010 '
b1101010 <
b1101010 8
b1010 .
b1010 ;
b1010 Q
1)
11
b10100110110000 %
b10100110110000 P
b1 &
b1 m
05
#510
b1100 !
b1100 p
b1100 0"
b1100 '
b1100 <
b1100 8
b1011 9
b1011 "
b1011 =
b1011 o
b1011 /"
b1101010 $
b1101010 n
b1101010 *"
15
#520
b0 9
b0 !
b0 p
b0 0"
b0 '
b0 <
b0 8
b0 .
b0 ;
b0 Q
0)
01
1/
b1100010000 %
b1100010000 P
b10 &
b10 m
05
#530
b1101010 "
b1101010 =
b1101010 o
b1101010 /"
b0 $
b0 n
b0 *"
15
#540
b1101010 9
b1101011 !
b1101011 p
b1101011 0"
b1101011 '
b1101011 <
b1101011 8
b1010 .
b1010 ;
b1010 Q
1)
11
0/
b10100110110000 %
b10100110110000 P
b11 &
b11 m
05
#550
b1011 !
b1011 p
b1011 0"
b1011 '
b1011 <
b1011 8
b1010 9
b1010 "
b1010 =
b1010 o
b1010 /"
b1101011 $
b1101011 n
b1101011 *"
15
#560
b11110101 9
b11101011 !
b11101011 p
b11101011 0"
b11101011 '
b11101011 <
b111101011 8
b11110101 :
b101 .
b101 ;
b101 Q
13
12
1+
0,
0)
0-
b1010010000111 %
b1010010000111 P
b100 &
b100 m
05
#570
b11100001 !
b11100001 p
b11100001 0"
b11100001 '
b11100001 <
b111100001 8
b11101011 :
b11101011 (
b11101011 >
b11101011 2"
15
#580
b0 9
b11101011 !
b11101011 p
b11101011 0"
b11101011 '
b11101011 <
b11101011 8
b0 .
b0 ;
b0 Q
03
02
0+
01
b0 %
b0 P
b101 &
b101 m
05
#590
15
#600
b110 &
b110 m
05
#610
15
#620
b111 &
b111 m
05
#630
15
#640
b0 !
b0 p
b0 0"
b0 '
b0 <
b0 8
b0 :
1,
1-
b100010000 %
b100010000 P
b0 &
b0 m
05
#650
b1101011 "
b1101011 =
b1101011 o
b1101011 /"
b0 $
b0 n
b0 *"
15
#660
b1101011 9
b1101100 !
b1101100 p
b1101100 0"
b1101100 '
b1101100 <
b1101100 8
b1010 .
b1010 ;
b1010 Q
1)
11
b10100110110000 %
b10100110110000 P
b1 &
b1 m
05
#670
b1100 !
b1100 p
b1100 0"
b1100 '
b1100 <
b1100 8
b1011 9
b1011 "
b1011 =
b1011 o
b1011 /"
b1101100 $
b1101100 n
b1101100 *"
15
#680
b0 9
b0 !
b0 p
b0 0"
b0 '
b0 <
b0 8
b0 .
b0 ;
b0 Q
0)
01
1/
b1100010000 %
b1100010000 P
b10 &
b10 m
05
#690
b1101100 "
b1101100 =
b1101100 o
b1101100 /"
b0 $
b0 n
b0 *"
15
#700
b1101100 9
b1101101 !
b1101101 p
b1101101 0"
b1101101 '
b1101101 <
b1101101 8
b1010 .
b1010 ;
b1010 Q
1)
11
0/
b10100110110000 %
b10100110110000 P
b11 &
b11 m
05
#710
b1011 !
b1011 p
b1011 0"
b1011 '
b1011 <
b1011 8
b1010 9
b1010 "
b1010 =
b1010 o
b1010 /"
b1101101 $
b1101101 n
b1101101 *"
15
#720
b11110101 9
b11100001 !
b11100001 p
b11100001 0"
b11100001 '
b11100001 <
b111100001 8
b11101011 :
b101 .
b101 ;
b101 Q
13
12
1+
0,
0)
0-
b1010010000111 %
b1010010000111 P
b100 &
b100 m
05
#730
b11010111 !
b11010111 p
b11010111 0"
b11010111 '
b11010111 <
b111010111 8
b11100001 :
b11100001 (
b11100001 >
b11100001 2"
15
#740
b0 9
b11100001 !
b11100001 p
b11100001 0"
b11100001 '
b11100001 <
b11100001 8
b0 .
b0 ;
b0 Q
03
02
0+
01
b0 %
b0 P
b101 &
b101 m
05
#750
15
#760
b110 &
b110 m
05
#770
15
#780
b111 &
b111 m
05
#790
15
#800
b0 !
b0 p
b0 0"
b0 '
b0 <
b0 8
b0 :
1,
1-
b100010000 %
b100010000 P
b0 &
b0 m
05
#810
b1101101 "
b1101101 =
b1101101 o
b1101101 /"
b0 $
b0 n
b0 *"
15
#820
b1101101 9
b1101110 !
b1101110 p
b1101110 0"
b1101110 '
b1101110 <
b1101110 8
b1010 .
b1010 ;
b1010 Q
1)
11
b10100110110000 %
b10100110110000 P
b1 &
b1 m
05
#830
b1000011 !
b1000011 p
b1000011 0"
b1000011 '
b1000011 <
b1000011 8
b1000010 9
b1000010 "
b1000010 =
b1000010 o
b1000010 /"
b1101110 $
b1101110 n
b1101110 *"
15
#840
b0 9
b0 !
b0 p
b0 0"
b0 '
b0 <
b0 8
b0 .
b0 ;
b0 Q
0)
01
1/
b1100010000 %
b1100010000 P
b10 &
b10 m
05
#850
0J
1I
b10 O
b1000010 6
b1000010 M
b1101110 "
b1101110 =
b1101110 o
b1101110 /"
b0 $
b0 n
b0 *"
15
#860
b1101110 9
b1101111 !
b1101111 p
b1101111 0"
b1101111 '
b1101111 <
b1101111 8
b1010 .
b1010 ;
b1010 Q
1)
11
0/
b10100110110000 %
b10100110110000 P
b11 &
b11 m
05
#870
b1110 !
b1110 p
b1110 0"
b1110 '
b1110 <
b1110 8
b1101 9
b1101 "
b1101 =
b1101 o
b1101 /"
b1101111 $
b1101111 n
b1101111 *"
15
#880
b1101 !
b1101 p
b1101 0"
b1101 '
b1101 <
b1101 8
0)
01
b10100100010000 %
b10100100010000 P
b100 &
b100 m
05
#890
b1001 !
b1001 p
b1001 0"
b1001 '
b1001 <
b1001 8
b1001 9
b1001 "
b1001 =
b1001 o
b1001 /"
b1101 $
b1101 n
b1101 *"
15
#900
b11100001 !
b11100001 p
b11100001 0"
b11100001 '
b11100001 <
b11100001 8
b11100001 9
b1100 .
b1100 ;
b1100 Q
0,
1)
b11000100100000 %
b11000100100000 P
b101 &
b101 m
05
#910
b11100001 "
b11100001 =
b11100001 o
b11100001 /"
15
#920
b0 9
b11100001 !
b11100001 p
b11100001 0"
b11100001 '
b11100001 <
b11100001 8
b11100001 :
b0 .
b0 ;
b0 Q
0)
0-
b0 %
b0 P
b110 &
b110 m
05
#930
15
#940
b111 &
b111 m
05
#950
15
#960
b0 !
b0 p
b0 0"
b0 '
b0 <
b0 8
b0 :
1,
1-
b100010000 %
b100010000 P
b0 &
b0 m
05
#970
b1101111 "
b1101111 =
b1101111 o
b1101111 /"
b0 $
b0 n
b0 *"
15
#980
b1101111 9
b1110000 !
b1110000 p
b1110000 0"
b1110000 '
b1110000 <
b1110000 8
b1010 .
b1010 ;
b1010 Q
1)
11
b10100110110000 %
b10100110110000 P
b1 &
b1 m
05
#990
b1001100 !
b1001100 p
b1001100 0"
b1001100 '
b1001100 <
b1001100 8
b1001011 9
b1001011 "
b1001011 =
b1001011 o
b1001011 /"
b1110000 $
b1110000 n
b1110000 *"
15
