tiny.sv


module alu16 #(parameter WIDTH = 16) (clk, reset, A, B, E, L, LS, Cn, PI, PS, psr);
	input [WIDTH - 1:0] A, B;
	input [3:0] L;
	input Cn;
	input clk;
	input reset;
	input LS;
	input PI, PS;

	output [WIDTH - 1:0] E;
	output reg [3:0] psr;

	wire [WIDTH - 1:0] lA;
	wire [WIDTH - 1:0] lB;
	wire [WIDTH:0] tE;
	
	assign lA = LS ? 0: A;
	assign tE = { 1'b0, lA } + { 1'b0, lB } + (1 & Cn);
	assign E = tE[WIDTH - 1:0];
	// assign psr_wire[3] = (E[WIDTH - 1] & ~A[WIDTH - 1] & (lB[WIDTH - 1] == 0)) | (~E[WIDTH - 1] & A[WIDTH - 1] & lB[WIDTH - 1]);
	
	genvar i;

	for (i = 0; i < WIDTH; i = i + 1)
		assign lB[i] = A[i] ? (B[i] ? L[3] : L[2]) : (B[i] ? L[1] : L[0]);

	always @(posedge clk or negedge reset) begin
		if (reset == 1)
			psr <= 0;
		else
		if (PI == 1) begin
			psr[0] <= tE[WIDTH];
			psr[1] <= E[WIDTH - 1];
			psr[2] <= (E[WIDTH - 1: 0] == 0) ? 1: 0;
			psr[3] <= 0;

			// if (PS == 1) begin
			// end
			// else begin
			//     psr <= psr_wire;
			// end
		end
	end
endmodule


module sync_mux_2x1 #(parameter WIDTH = 16) (clk, reset, sel, enable, in0, in1, out);
	input sel, enable, clk, reset;
	input [WIDTH - 1:0] in0, in1;

	output reg [WIDTH - 1:0] out;

	always @(posedge clk or posedge reset) begin
		if (reset == 1)
			out = 0;
		else
		if (enable) begin
			if (sel == 1)
				out = in1;
			else
				out = in0;
		end
	end
endmodule


module memory #(parameter WIDTH = 16) (clk, reset, MI, RI, write, read);
	parameter imm = 0 << 6;
	parameter abs = 1 << 6;
	parameter off = 2 << 6;

	parameter loadi	= 	5'b00001;
	parameter loada =	loadi | abs;

	parameter store = 	5'b00010 | abs;

	parameter jump 	= 	5'b00100 | abs;
	parameter jumpz =	5'b00101 | abs;
	parameter jumpc =	5'b00110 | abs;
	parameter jumpn =	5'b00111 | abs;

	parameter add 	= 	6'b100000;
	parameter adc 	= 	6'b100001;
	parameter sbb 	= 	6'b100010;
	parameter sub 	= 	6'b100011;

	parameter adda 	= 	add | abs;
	parameter adca 	= 	adc | abs;
	parameter sbba 	= 	sbb | abs;
	parameter suba 	= 	sub | abs;

	parameter tmp = 10;
	parameter first = 11;
	parameter second = 12;
	parameter count = 13;
	
	input clk, MI, RI;
	input reset;
	input [WIDTH - 1:0] write;
	
	output [WIDTH - 1:0] read;
	
	reg [WIDTH - 1:0] mem_addr_reg;
	reg [WIDTH - 1:0] ram [2**WIDTH - 1:0];
	
	wire [WIDTH - 1:0] mar;
	wire [WIDTH - 1:0] display;

	integer org, start, finish;
	integer i;
	
	assign mar = mem_addr_reg;
	assign read = ram[mem_addr_reg];
	assign display = ram[first];

	always @(posedge clk or posedge reset) begin
		if (reset == 1) begin
			start = 100;
			finish = 200;
			
			mem_addr_reg <= 0;

			for (i = 0; i < 2**(WIDTH - 1); i++)
				ram[i] = 0;
			
			org = start;

			ram[0] = org - 1;

			ram[first] = 0;
			ram[second] = 1;
			ram[count] = 7;

			start = org++;

			ram[start] = loada; ram[org++] = count;
			ram[org++] = sbb; ram[org++] = 0;
			ram[org++] = store; ram[org++] = count;

			ram[org++] = jumpz; ram[org++] = finish - 1;
			
			ram[org++] = loada; ram[org++] = second;
			ram[org++] = store; ram[org++] = tmp;

			ram[org++] = adda; ram[org++] = first;
			ram[org++] = store; ram[org++] = second;

			ram[org++] = loada; ram[org++] = tmp;
			ram[org++] = store; ram[org++] = first;
			
			ram[org++] = jump; ram[org++] = start - 1;

			ram[finish] = 8'hff;
		end else begin
			if (MI == 1)
				mem_addr_reg <= write;

			if (RI == 1)
				ram[mem_addr_reg] <= write;
		end
	end
endmodule

module counter(clk, reset, clear, data);
	input clk;
	input reset;
	input clear;
	
	output reg [2:0] data;

	always @(negedge clk or posedge reset or posedge clear) begin
		if (reset == 1 || clear == 1) begin
			data <= 0;
		end else begin
			data <= data + 1;
		end
	end
endmodule

module controlunit(clk, reset, inst, psr, cAI, cAS, cPI, cPS, cMI, cRI, cES, cCn, cL, cLS, cII);
	// Enable Control Lines

	parameter AI = 1 << 0;
	parameter AS = 1 << 1;
	parameter PI = 1 << 2;
	parameter PS = 1 << 3;
	parameter MI = 1 << 4;
	parameter RI = 1 << 5;
	parameter ES = 1 << 6;
	parameter Cn = 1 << 7;
	parameter LS = 1 << 8;
	parameter II = 1 << 9;
	parameter CR = 1 << 10;

	// ALU Control Lines

	parameter GEN_0 = 15'b0000_00000000000 | LS;
	parameter GEN_1 = 15'b1111_00000000000 | LS;
	parameter BUF_A = 15'b1100_00000000000;
	parameter NEG_A = 15'b0011_00000000000;
	parameter BUF_B = 15'b1010_00000000000;
	parameter NEG_B = 15'b0101_00000000000;

	parameter load 	= 	6'b000001;
	parameter loadi = 	6'b000001;

	parameter store = 	6'b000010;

	parameter jump 	= 	6'b000100;
	parameter jumpz =	6'b000101;
	parameter jumpc =	6'b000110;
	parameter jumpn =	6'b000111;

	parameter add 	= 	6'b100000;
	parameter addc 	= 	6'b100001;
	parameter subb 	= 	6'b100010;
	parameter sub 	= 	6'b100011;
	
	parameter logic_nand = 	6'b010100;
	parameter logic_and = 	6'b010101;
	
	parameter logic_nor = 	6'b010110;
	parameter logic_or = 	6'b010111;
	
	parameter logic_xnor = 	6'b011000;
	parameter logic_xor = 	6'b011001;

	input clk;
	input reset;
	input [7:0] inst;
	input [3:0] psr;

	output cAI, cAS;
	output cPI, cPS;
	output cMI, cRI;
	output cES;
	output cCn;
	output cLS;
	output cII;
	output [3:0] cL;

	reg [2:0] counter;
	
	wire [15:0] decode;
	wire [2:0] res_counter;
	wire TYPE_REG, TYPE_IMM, TYPE_ABS, TYPE_OFF;
	wire [5:0] opcode;

	assign TYPE_IMM = ~inst[7] & ~inst[6];	// 0
	assign TYPE_ABS = ~inst[7] & inst[6];	// 1
	assign TYPE_OFF = inst[7] & ~inst[6];	// 2
	assign TYPE_REG = inst[7] & inst[6];	// 3

	assign opcode = inst[5:0];
	
	assign cAI = decode[0];
	assign cAS = decode[1];
	assign cPI = decode[2];
	assign cPS = decode[3];
	assign cMI = decode[4];
	assign cRI = decode[5];
	assign cES = decode[6];
	assign cCn = decode[7];
	assign cLS = decode[8];
	assign cII = decode[9];
	// assign res_counter = decode[10];
	assign cL = decode[15:11];

	always @(negedge clk or posedge reset or posedge (decode == 0)) begin
		if (reset == 1 || decode == 0) begin
			counter <= 0;
		end else begin
			counter <= counter + 1;
		end
	end
	
	assign decode =
		counter == 0 ? GEN_0 | MI:
		counter == 1 ? BUF_B | Cn | MI | RI | LS:
		counter == 2 ? II | GEN_0 | MI:
		counter == 3 ? BUF_B | Cn | MI | RI | LS:
		counter == 4 ?
			TYPE_IMM ?
				opcode == load ? AI:

				opcode == add ? BUF_B | PI | AS | AI:
				opcode == addc ? BUF_B | PI | AS | AI | Cn:
				opcode == subb ? NEG_B | PI | AS | AI:
				opcode == sub ? NEG_B | PI | AS | AI | Cn:
				0:
			TYPE_ABS ?
				opcode == load ? BUF_B | MI | LS:

				opcode == store ? BUF_B | MI | LS:

				((opcode == jump) |
				((opcode == jumpz) & (psr[2] == 1)) |
				((opcode == jumpc) & (psr[0] == 1)) |
				((opcode == jumpn) & (psr[1] == 1))) ? GEN_0 | MI | AI:

				opcode == add ? BUF_B | MI | LS:
				opcode == addc ? BUF_B | MI | LS:
				opcode == sub ? BUF_B | MI | LS:
				opcode == subb ? BUF_B | MI | LS:
				0:
			0:
		counter == 5 ?
			TYPE_ABS ?
				opcode == load ? AI:

				opcode == store ? BUF_A | RI | LS:

				((opcode == jump) |
				((opcode == jumpz) & (psr[2] == 1)) |
				((opcode == jumpc) & (psr[0] == 1)) |
				((opcode == jumpn) & (psr[1] == 1))) ? BUF_A | MI | RI | LS:

				opcode == add ? BUF_B | PI | AS | AI:
				opcode == addc ? BUF_B | PI | AS | AI | Cn:
				opcode == subb ? NEG_B | PI | AS | AI:
				opcode == sub ? NEG_B | PI | AS | AI | Cn:
				0:
			0:
		0;
endmodule

module instructionregister #(parameter WIDTH = 16) (clk, reset, halt, enable, data_in, inst);
	input clk;
	input reset;
	input enable;
	input [WIDTH - 1:0] data_in;

	output reg halt;
	output reg [7:0] inst;
	
	always @(posedge clk or posedge reset) begin
		if (inst == 2**WIDTH - 1)
			halt <= 1;
		else if (reset == 1)
			inst <= 0;
		else if (enable == 1) begin
			inst <= data_in;
			halt <= 0;
		end
	end
endmodule

module processor #(parameter WIDTH = 16)(clk, reset, halt);
	input clk;
	input reset;

	output halt;
	
	wire [WIDTH - 1:0] accumulator_bus;
	wire [WIDTH - 1:0] ram_read_bus;
	wire [WIDTH - 1:0] ram_write_bus;
	wire [WIDTH - 1:0] alu_out_bus;
	wire [3:0] psr_bus;
	wire [7:0] inst;
	
	wire AI, AS;
	wire PI, PS;
	wire MI, RI;
	wire ES;
	wire C_in;
	wire LS;
	wire II;
	wire [3:0] L;
	
	alu16 #(WIDTH) alu (clk, reset, accumulator_bus, ram_read_bus, alu_out_bus, L, LS, C_in, PI, PS, psr_bus);
	
	// ES == 0 -> ALU
	// ES == 1 -> PSR
	assign ram_write_bus = ES ? psr_bus: alu_out_bus;
	
	sync_mux_2x1 #(WIDTH) rega_mux(clk, reset, AS, AI, ram_read_bus, ram_write_bus, accumulator_bus);
	
	memory #(WIDTH) ram(clk, reset, MI, RI, ram_write_bus, ram_read_bus);
	
	controlunit cu(clk, reset, inst, psr_bus, AI, AS, PI, PS, MI, RI, ES, C_in, L, LS, II);

	instructionregister #(WIDTH) ir(clk, reset, halt, II, ram_read_bus, inst);
endmodule


module testbench;
	reg clk;
	reg reset;

	wire halt;

	processor #(8) tiny(clk, reset, halt);
	
	initial begin
		clk = 0;
		reset = 1;

		forever begin
			#1 clk = ~clk;
			if (reset == 1 & clk)
				reset = 0;
			else if (halt)
				$finish;
		end
	end

	initial begin
		$dumpfile ("testbench.vcd");
		$dumpvars (0, testbench);

		$monitor ($time, ":\tclk=%B | reset=%B | halt=%B", clk, reset, halt);

		#2000
		$finish;
	end
endmodule

testbench.vcd
$date
	Sun Dec 17 17:18:06 2023
$end
$version
	Icarus Verilog
$end
$timescale
	1s
$end
$scope module testbench $end
$var wire 1 ! halt $end
$var reg 1 " clk $end
$var reg 1 # reset $end
$scope module tiny $end
$var wire 1 " clk $end
$var wire 1 # reset $end
$var wire 8 $ ram_write_bus [7:0] $end
$var wire 8 % ram_read_bus [7:0] $end
$var wire 4 & psr_bus [3:0] $end
$var wire 8 ' alu_out_bus [7:0] $end
$var wire 8 ( accumulator_bus [7:0] $end
$var wire 1 ) RI $end
$var wire 1 * PS $end
$var wire 1 + PI $end
$var wire 1 , MI $end
$var wire 1 - LS $end
$var wire 4 . L [3:0] $end
$var wire 1 / II $end
$var wire 1 0 ES $end
$var wire 1 1 C_in $end
$var wire 1 2 AS $end
$var wire 1 3 AI $end
$var parameter 32 4 WIDTH $end
$var reg 1 ! halt $end
$var reg 8 5 inst [7:0] $end
$scope module alu $end
$var wire 1 " clk $end
$var wire 1 # reset $end
$var wire 9 6 tE [8:0] $end
$var wire 8 7 lB [7:0] $end
$var wire 8 8 lA [7:0] $end
$var wire 1 * PS $end
$var wire 1 + PI $end
$var wire 1 - LS $end
$var wire 4 9 L [3:0] $end
$var wire 8 : E [7:0] $end
$var wire 1 1 Cn $end
$var wire 8 ; B [7:0] $end
$var wire 8 < A [7:0] $end
$var parameter 32 = WIDTH $end
$var reg 4 > psr [3:0] $end
$scope begin genblk1[0] $end
$var parameter 2 ? i $end
$upscope $end
$scope begin genblk1[1] $end
$var parameter 2 @ i $end
$upscope $end
$scope begin genblk1[2] $end
$var parameter 3 A i $end
$upscope $end
$scope begin genblk1[3] $end
$var parameter 3 B i $end
$upscope $end
$scope begin genblk1[4] $end
$var parameter 4 C i $end
$upscope $end
$scope begin genblk1[5] $end
$var parameter 4 D i $end
$upscope $end
$scope begin genblk1[6] $end
$var parameter 4 E i $end
$upscope $end
$scope begin genblk1[7] $end
$var parameter 4 F i $end
$upscope $end
$upscope $end
$scope module cu $end
$var wire 1 G TYPE_ABS $end
$var wire 1 H TYPE_IMM $end
$var wire 1 I TYPE_OFF $end
$var wire 1 J TYPE_REG $end
$var wire 1 " clk $end
$var wire 8 K inst [7:0] $end
$var wire 4 L psr [3:0] $end
$var wire 1 # reset $end
$var wire 6 M opcode [5:0] $end
$var wire 16 N decode [15:0] $end
$var wire 1 ) cRI $end
$var wire 1 * cPS $end
$var wire 1 + cPI $end
$var wire 1 , cMI $end
$var wire 1 - cLS $end
$var wire 4 O cL [3:0] $end
$var wire 1 / cII $end
$var wire 1 0 cES $end
$var wire 1 1 cCn $end
$var wire 1 2 cAS $end
$var wire 1 3 cAI $end
$var parameter 32 P AI $end
$var parameter 33 Q AS $end
$var parameter 15 R BUF_A $end
$var parameter 15 S BUF_B $end
$var parameter 42 T CR $end
$var parameter 39 U Cn $end
$var parameter 38 V ES $end
$var parameter 40 W GEN_0 $end
$var parameter 40 X GEN_1 $end
$var parameter 41 Y II $end
$var parameter 40 Z LS $end
$var parameter 36 [ MI $end
$var parameter 15 \ NEG_A $end
$var parameter 15 ] NEG_B $end
$var parameter 34 ^ PI $end
$var parameter 35 _ PS $end
$var parameter 37 ` RI $end
$var parameter 6 a add $end
$var parameter 6 b addc $end
$var parameter 6 c jump $end
$var parameter 6 d jumpc $end
$var parameter 6 e jumpn $end
$var parameter 6 f jumpz $end
$var parameter 6 g load $end
$var parameter 6 h loadi $end
$var parameter 6 i logic_and $end
$var parameter 6 j logic_nand $end
$var parameter 6 k logic_nor $end
$var parameter 6 l logic_or $end
$var parameter 6 m logic_xnor $end
$var parameter 6 n logic_xor $end
$var parameter 6 o store $end
$var parameter 6 p sub $end
$var parameter 6 q subb $end
$var reg 3 r counter [2:0] $end
$upscope $end
$scope module ram $end
$var wire 1 , MI $end
$var wire 1 ) RI $end
$var wire 1 " clk $end
$var wire 8 s display [7:0] $end
$var wire 8 t mar [7:0] $end
$var wire 8 u read [7:0] $end
$var wire 1 # reset $end
$var wire 8 v write [7:0] $end
$var parameter 32 w WIDTH $end
$var parameter 38 x abs $end
$var parameter 6 y adc $end
$var parameter 38 z adca $end
$var parameter 6 { add $end
$var parameter 38 | adda $end
$var parameter 32 } count $end
$var parameter 32 ~ first $end
$var parameter 38 !" imm $end
$var parameter 38 "" jump $end
$var parameter 38 #" jumpc $end
$var parameter 38 $" jumpn $end
$var parameter 38 %" jumpz $end
$var parameter 38 &" loada $end
$var parameter 5 '" loadi $end
$var parameter 38 (" off $end
$var parameter 6 )" sbb $end
$var parameter 38 *" sbba $end
$var parameter 32 +" second $end
$var parameter 38 ," store $end
$var parameter 6 -" sub $end
$var parameter 38 ." suba $end
$var parameter 32 /" tmp $end
$var reg 8 0" mem_addr_reg [7:0] $end
$var integer 32 1" finish [31:0] $end
$var integer 32 2" i [31:0] $end
$var integer 32 3" org [31:0] $end
$var integer 32 4" start [31:0] $end
$upscope $end
$scope module rega_mux $end
$var wire 1 " clk $end
$var wire 1 3 enable $end
$var wire 8 5" in0 [7:0] $end
$var wire 8 6" in1 [7:0] $end
$var wire 1 # reset $end
$var wire 1 2 sel $end
$var parameter 32 7" WIDTH $end
$var reg 8 8" out [7:0] $end
$upscope $end
$upscope $end
$upscope $end
$enddefinitions $end
$comment Show the parameter values. $end
$dumpall
b1000 7"
b1010 /"
b1100011 ."
b100011 -"
b1000010 ,"
b1100 +"
b1100010 *"
b100010 )"
b10000000 ("
b1 '"
b1000001 &"
b1000101 %"
b1000111 $"
b1000110 #"
b1000100 ""
b0 !"
b1011 ~
b1101 }
b1100000 |
b100000 {
b1100001 z
b100001 y
b1000000 x
b1000 w
b100010 q
b100011 p
b10 o
b11001 n
b11000 m
b10111 l
b10110 k
b10100 j
b10101 i
b1 h
b1 g
b101 f
b111 e
b110 d
b100 c
b100001 b
b100000 a
b100000 `
b1000 _
b100 ^
b10100000000000 ]
b1100000000000 \
b10000 [
b100000000 Z
b1000000000 Y
b111100100000000 X
b100000000 W
b1000000 V
b10000000 U
b10000000000 T
b101000000000000 S
b110000000000000 R
b10 Q
b1 P
b111 F
b110 E
b101 D
b100 C
b11 B
b10 A
b1 @
b0 ?
b1000 =
b1000 4
$end
#0
$dumpvars
b0 8"
b0 6"
b1100011 5"
b1100100 4"
b1111010 3"
b10000000 2"
b11001000 1"
b0 0"
b0 v
b1100011 u
b0 t
b0 s
b0 r
b0 O
b100010000 N
b0 M
bx L
b0 K
0J
0I
1H
0G
bx >
b0 <
b1100011 ;
b0 :
b0 9
b0 8
b0 7
b0 6
b0 5
03
02
01
00
0/
b0 .
1-
1,
0+
0*
0)
b0 (
b0 '
bx &
b1100011 %
b0 $
1#
0"
x!
$end
#1
0#
1"
#2
b1100011 7
b1100100 $
b1100100 v
b1100100 6"
b1100100 '
b1100100 :
b1100100 6
b1010 .
b1010 9
b1010 O
1)
11
b101000110110000 N
b1 r
0"
#3
b1000010 $
b1000010 v
b1000010 6"
b1000010 '
b1000010 :
b1000010 6
b1000001 7
b1000001 %
b1000001 ;
b1000001 u
b1000001 5"
b1100100 t
b1100100 0"
1"
#4
b0 7
b0 $
b0 v
b0 6"
b0 '
b0 :
b0 6
b0 .
b0 9
b0 O
0)
01
1/
b1100010000 N
b10 r
0"
#5
0H
1G
b1 M
0!
b1000001 5
b1000001 K
b1100100 %
b1100100 ;
b1100100 u
b1100100 5"
b0 t
b0 0"
1"
#6
b1100100 7
b1100101 $
b1100101 v
b1100101 6"
b1100101 '
b1100101 :
b1100101 6
b1010 .
b1010 9
b1010 O
1)
11
0/
b101000110110000 N
b11 r
0"
#7
b1110 $
b1110 v
b1110 6"
b1110 '
b1110 :
b1110 6
b1101 7
b1101 %
b1101 ;
b1101 u
b1101 5"
b1100101 t
b1100101 0"
1"
#8
b1101 $
b1101 v
b1101 6"
b1101 '
b1101 :
b1101 6
0)
01
b101000100010000 N
b100 r
0"
#9
b111 $
b111 v
b111 6"
b111 '
b111 :
b111 6
b111 7
b111 %
b111 ;
b111 u
b111 5"
b1101 t
b1101 0"
1"
#10
b0 $
b0 v
b0 6"
b0 '
b0 :
b0 6
b0 7
b0 .
b0 9
b0 O
13
0,
0-
b1 N
b101 r
0"
#11
b111 $
b111 v
b111 6"
b111 '
b111 :
b111 6
b111 8
b111 (
b111 <
b111 8"
1"
#12
b0 $
b0 v
b0 6"
b0 '
b0 :
b0 6
b0 8
1,
1-
03
b100010000 N
b0 r
0"
#13
b1100101 %
b1100101 ;
b1100101 u
b1100101 5"
b0 t
b0 0"
1"
#14
b1100101 7
b1100110 $
b1100110 v
b1100110 6"
b1100110 '
b1100110 :
b1100110 6
b1010 .
b1010 9
b1010 O
1)
11
b101000110110000 N
b1 r
0"
#15
b100011 $
b100011 v
b100011 6"
b100011 '
b100011 :
b100011 6
b100010 7
b100010 %
b100010 ;
b100010 u
b100010 5"
b1100110 t
b1100110 0"
1"
#16
b0 7
b0 $
b0 v
b0 6"
b0 '
b0 :
b0 6
b0 .
b0 9
b0 O
0)
01
1/
b1100010000 N
b10 r
0"
#17
1H
0G
b100010 M
b100010 5
b100010 K
b1100110 %
b1100110 ;
b1100110 u
b1100110 5"
b0 t
b0 0"
1"
#18
b1100110 7
b1100111 $
b1100111 v
b1100111 6"
b1100111 '
b1100111 :
b1100111 6
b1010 .
b1010 9
b1010 O
1)
11
0/
b101000110110000 N
b11 r
0"
#19
b1 $
b1 v
b1 6"
b1 '
b1 :
b1 6
b0 7
b0 %
b0 ;
b0 u
b0 5"
b1100111 t
b1100111 0"
1"
#20
b11111111 7
b110 $
b110 v
b110 6"
b110 '
b110 :
b100000110 6
b111 8
b101 .
b101 9
b101 O
13
12
1+
0,
0)
01
0-
b10100000000111 N
b100 r
0"
#21
b1 &
b1 >
b1 L
b101 $
b101 v
b101 6"
b101 '
b101 :
b100000101 6
b110 8
b110 (
b110 <
b110 8"
1"
#22
b0 8
1,
1-
b0 $
b0 v
b0 6"
b0 '
b0 :
b0 6
b0 7
b0 .
b0 9
b0 O
03
02
0+
b100010000 N
b0 r
0"
#23
b1100111 %
b1100111 ;
b1100111 u
b1100111 5"
b0 t
b0 0"
1"
#24
b1100111 7
b1101000 $
b1101000 v
b1101000 6"
b1101000 '
b1101000 :
b1101000 6
b1010 .
b1010 9
b1010 O
1)
11
b101000110110000 N
b1 r
0"
#25
b1000011 $
b1000011 v
b1000011 6"
b1000011 '
b1000011 :
b1000011 6
b1000010 7
b1000010 %
b1000010 ;
b1000010 u
b1000010 5"
b1101000 t
b1101000 0"
1"
#26
b0 7
b0 $
b0 v
b0 6"
b0 '
b0 :
b0 6
b0 .
b0 9
b0 O
0)
01
1/
b1100010000 N
b10 r
0"
#27
0H
1G
b10 M
b1101000 %
b1101000 ;
b1101000 u
b1101000 5"
b0 t
b0 0"
b1000010 5
b1000010 K
1"
#28
b1101000 7
b1101001 $
b1101001 v
b1101001 6"
b1101001 '
b1101001 :
b1101001 6
b1010 .
b1010 9
b1010 O
1)
11
0/
b101000110110000 N
b11 r
0"
#29
b1110 $
b1110 v
b1110 6"
b1110 '
b1110 :
b1110 6
b1101 7
b1101 %
b1101 ;
b1101 u
b1101 5"
b1101001 t
b1101001 0"
1"
#30
b1101 $
b1101 v
b1101 6"
b1101 '
b1101 :
b1101 6
0)
01
b101000100010000 N
b100 r
0"
#31
b111 $
b111 v
b111 6"
b111 '
b111 :
b111 6
b111 7
b111 %
b111 ;
b111 u
b111 5"
b1101 t
b1101 0"
1"
#32
b110 $
b110 v
b110 6"
b110 '
b110 :
b110 6
b110 7
b1100 .
b1100 9
b1100 O
0,
1)
b110000100100000 N
b101 r
0"
#33
b110 %
b110 ;
b110 u
b110 5"
1"
#34
1,
b0 7
b0 $
b0 v
b0 6"
b0 '
b0 :
b0 6
b0 8
b0 .
b0 9
b0 O
0)
1-
b100010000 N
b0 r
0"
#35
b1101001 %
b1101001 ;
b1101001 u
b1101001 5"
b0 t
b0 0"
1"
#36
b1101001 7
b1101010 $
b1101010 v
b1101010 6"
b1101010 '
b1101010 :
b1101010 6
b1010 .
b1010 9
b1010 O
1)
11
b101000110110000 N
b1 r
0"
#37
b1000110 $
b1000110 v
b1000110 6"
b1000110 '
b1000110 :
b1000110 6
b1000101 7
b1000101 %
b1000101 ;
b1000101 u
b1000101 5"
b1101010 t
b1101010 0"
1"
#38
b0 7
b0 $
b0 v
b0 6"
b0 '
b0 :
b0 6
b0 .
b0 9
b0 O
0)
01
1/
b1100010000 N
b10 r
0"
#39
b101 M
b1101010 %
b1101010 ;
b1101010 u
b1101010 5"
b0 t
b0 0"
b1000101 5
b1000101 K
1"
#40
b1101010 7
b1101011 $
b1101011 v
b1101011 6"
b1101011 '
b1101011 :
b1101011 6
b1010 .
b1010 9
b1010 O
1)
11
0/
b101000110110000 N
b11 r
0"
#41
b11001000 $
b11001000 v
b11001000 6"
b11001000 '
b11001000 :
b11001000 6
b11000111 7
b11000111 %
b11000111 ;
b11000111 u
b11000111 5"
b1101011 t
b1101011 0"
1"
#42
b0 7
b0 $
b0 v
b0 6"
b0 '
b0 :
b0 6
b0 8
b0 .
b0 9
b0 O
1,
0)
01
1-
b100010000 N
b0 r
0"
#43
b1101011 %
b1101011 ;
b1101011 u
b1101011 5"
b0 t
b0 0"
1"
#44
b1101011 7
b1101100 $
b1101100 v
b1101100 6"
b1101100 '
b1101100 :
b1101100 6
b1010 .
b1010 9
b1010 O
1)
11
b101000110110000 N
b1 r
0"
#45
b1000010 $
b1000010 v
b1000010 6"
b1000010 '
b1000010 :
b1000010 6
b1000001 7
b1000001 %
b1000001 ;
b1000001 u
b1000001 5"
b1101100 t
b1101100 0"
1"
#46
b0 7
b0 $
b0 v
b0 6"
b0 '
b0 :
b0 6
b0 .
b0 9
b0 O
0)
01
1/
b1100010000 N
b10 r
0"
#47
b1 M
b1101100 %
b1101100 ;
b1101100 u
b1101100 5"
b0 t
b0 0"
b1000001 5
b1000001 K
1"
#48
b1101100 7
b1101101 $
b1101101 v
b1101101 6"
b1101101 '
b1101101 :
b1101101 6
b1010 .
b1010 9
b1010 O
1)
11
0/
b101000110110000 N
b11 r
0"
#49
b1101 $
b1101 v
b1101 6"
b1101 '
b1101 :
b1101 6
b1100 7
b1100 %
b1100 ;
b1100 u
b1100 5"
b1101101 t
b1101101 0"
1"
#50
b1100 $
b1100 v
b1100 6"
b1100 '
b1100 :
b1100 6
0)
01
b101000100010000 N
b100 r
0"
#51
b1 $
b1 v
b1 6"
b1 '
b1 :
b1 6
b1 7
b1 %
b1 ;
b1 u
b1 5"
b1100 t
b1100 0"
1"
#52
b0 7
b110 $
b110 v
b110 6"
b110 '
b110 :
b110 6
b110 8
b0 .
b0 9
b0 O
13
0,
0-
b1 N
b101 r
0"
#53
b1 $
b1 v
b1 6"
b1 '
b1 :
b1 6
b1 8
b1 (
b1 <
b1 8"
1"
#54
b0 $
b0 v
b0 6"
b0 '
b0 :
b0 6
b0 8
1,
1-
03
b100010000 N
b0 r
0"
#55
b1101101 %
b1101101 ;
b1101101 u
b1101101 5"
b0 t
b0 0"
1"
#56
b1101101 7
b1101110 $
b1101110 v
b1101110 6"
b1101110 '
b1101110 :
b1101110 6
b1010 .
b1010 9
b1010 O
1)
11
b101000110110000 N
b1 r
0"
#57
b1000011 $
b1000011 v
b1000011 6"
b1000011 '
b1000011 :
b1000011 6
b1000010 7
b1000010 %
b1000010 ;
b1000010 u
b1000010 5"
b1101110 t
b1101110 0"
1"
#58
b0 7
b0 $
b0 v
b0 6"
b0 '
b0 :
b0 6
b0 .
b0 9
b0 O
0)
01
1/
b1100010000 N
b10 r
0"
#59
b10 M
b1101110 %
b1101110 ;
b1101110 u
b1101110 5"
b0 t
b0 0"
b1000010 5
b1000010 K
1"
#60
b1101110 7
b1101111 $
b1101111 v
b1101111 6"
b1101111 '
b1101111 :
b1101111 6
b1010 .
b1010 9
b1010 O
1)
11
0/
b101000110110000 N
b11 r
0"
#61
b1011 $
b1011 v
b1011 6"
b1011 '
b1011 :
b1011 6
b1010 7
b1010 %
b1010 ;
b1010 u
b1010 5"
b1101111 t
b1101111 0"
1"
#62
b1010 $
b1010 v
b1010 6"
b1010 '
b1010 :
b1010 6
0)
01
b101000100010000 N
b100 r
0"
#63
b0 $
b0 v
b0 6"
b0 '
b0 :
b0 6
b0 7
b0 %
b0 ;
b0 u
b0 5"
b1010 t
b1010 0"
1"
#64
b1 $
b1 v
b1 6"
b1 '
b1 :
b1 6
b1 7
b1100 .
b1100 9
b1100 O
0,
1)
b110000100100000 N
b101 r
0"
#65
b1 %
b1 ;
b1 u
b1 5"
1"
#66
1,
b0 7
b0 $
b0 v
b0 6"
b0 '
b0 :
b0 6
b0 8
b0 .
b0 9
b0 O
0)
1-
b100010000 N
b0 r
0"
#67
b1101111 %
b1101111 ;
b1101111 u
b1101111 5"
b0 t
b0 0"
1"
#68
b1101111 7
b1110000 $
b1110000 v
b1110000 6"
b1110000 '
b1110000 :
b1110000 6
b1010 .
b1010 9
b1010 O
1)
11
b101000110110000 N
b1 r
0"
#69
b1100001 $
b1100001 v
b1100001 6"
b1100001 '
b1100001 :
b1100001 6
b1100000 7
b1100000 %
b1100000 ;
b1100000 u
b1100000 5"
b1110000 t
b1110000 0"
1"
#70
b0 7
b0 $
b0 v
b0 6"
b0 '
b0 :
b0 6
b0 .
b0 9
b0 O
0)
01
1/
b1100010000 N
b10 r
0"
#71
b100000 M
b1110000 %
b1110000 ;
b1110000 u
b1110000 5"
b0 t
b0 0"
b1100000 5
b1100000 K
1"
#72
b1110000 7
b1110001 $
b1110001 v
b1110001 6"
b1110001 '
b1110001 :
b1110001 6
b1010 .
b1010 9
b1010 O
1)
11
0/
b101000110110000 N
b11 r
0"
#73
b1100 $
b1100 v
b1100 6"
b1100 '
b1100 :
b1100 6
b1011 7
b1011 %
b1011 ;
b1011 u
b1011 5"
b1110001 t
b1110001 0"
1"
#74
b1011 $
b1011 v
b1011 6"
b1011 '
b1011 :
b1011 6
0)
01
b101000100010000 N
b100 r
0"
#75
b0 $
b0 v
b0 6"
b0 '
b0 :
b0 6
b0 7
b0 %
b0 ;
b0 u
b0 5"
b1011 t
b1011 0"
1"
#76
b1 $
b1 v
b1 6"
b1 '
b1 :
b1 6
b1 8
13
12
1+
0,
0-
b101000000000111 N
b101 r
0"
#77
b0 &
b0 >
b0 L
1"
#78
b0 $
b0 v
b0 6"
b0 '
b0 :
b0 6
b0 8
1,
1-
b0 .
b0 9
b0 O
03
02
0+
b100010000 N
b0 r
0"
#79
b1110001 %
b1110001 ;
b1110001 u
b1110001 5"
b0 t
b0 0"
1"
#80
b1110001 7
b1110010 $
b1110010 v
b1110010 6"
b1110010 '
b1110010 :
b1110010 6
b1010 .
b1010 9
b1010 O
1)
11
b101000110110000 N
b1 r
0"
#81
b1000011 $
b1000011 v
b1000011 6"
b1000011 '
b1000011 :
b1000011 6
b1000010 7
b1000010 %
b1000010 ;
b1000010 u
b1000010 5"
b1110010 t
b1110010 0"
1"
#82
b0 7
b0 $
b0 v
b0 6"
b0 '
b0 :
b0 6
b0 .
b0 9
b0 O
0)
01
1/
b1100010000 N
b10 r
0"
#83
b10 M
b1110010 %
b1110010 ;
b1110010 u
b1110010 5"
b0 t
b0 0"
b1000010 5
b1000010 K
1"
#84
b1110010 7
b1110011 $
b1110011 v
b1110011 6"
b1110011 '
b1110011 :
b1110011 6
b1010 .
b1010 9
b1010 O
1)
11
0/
b101000110110000 N
b11 r
0"
