tiny.sv


module alu16 #(parameter WIDTH = 16) (clk, reset, A, B, E, L, LS, Cn, PI, PS, psr);
	input [WIDTH - 1:0] A, B;
	input [3:0] L;
	input Cn;
	input clk;
	input reset;
	input LS;
	input PI, PS;

	output [WIDTH - 1:0] E;
	output reg [3:0] psr;

	wire [WIDTH - 1:0] lA;
	wire [WIDTH - 1:0] lB;
	wire [WIDTH:0] tE;

	genvar i;

	for (i = 0; i < WIDTH; i = i + 1)
		assign lB[i] = A[i] ? (B[i] ? L[3] : L[2]) : (B[i] ? L[1] : L[0]);

	assign lA = LS ? 0: A;
	assign tE = { 1'b0, lA } + { 1'b0, lB } + (1 & Cn);
	assign E = tE[WIDTH - 1:0];

	// assign psr_wire[3] = (E[WIDTH - 1] & ~A[WIDTH - 1] & (lB[WIDTH - 1] == 0)) | (~E[WIDTH - 1] & A[WIDTH - 1] & lB[WIDTH - 1]);

	always @(posedge clk or negedge reset) begin
		if (reset == 1) begin
			psr <= 0;
		end
		else
		if (PI == 1) begin
			psr[0] <= tE[WIDTH];
			psr[1] <= E[WIDTH - 1];
			psr[2] <= (E[WIDTH - 1: 0] == 0) ? 1: 0;
			psr[3] <= 0;

			// if (PS == 1) begin
			// end
			// else begin
			//     psr <= psr_wire;
			// end
		end
	end
endmodule


module sync_mux_2x1 #(parameter WIDTH = 16) (clk, reset, sel, enable, in0, in1, out);
	input sel, enable, clk, reset;
	input [WIDTH - 1:0] in0, in1;

	output reg [WIDTH - 1:0] out;

	always @(posedge clk or posedge reset) begin
		if (reset == 1)
			out = 0;
		else
		if (enable) begin
			if (sel == 1)
				out = in1;
			else
				out = in0;
		end
	end
endmodule


module memory #(parameter WIDTH = 16) (clk, reset, MI, RI, write, read, mar);
	input clk, MI, RI;
	input reset;
	
	output [WIDTH - 1:0] mar;
	input [WIDTH - 1:0] write;
	output [WIDTH - 1:0] read;
	
	reg [WIDTH - 1:0] mem_addr_reg;
	reg [WIDTH - 1:0] ram [2**WIDTH - 1:0];
	
	integer i;

	assign mar = mem_addr_reg;
	
	parameter imm = 0 << 6;
	parameter abs = 1 << 6;
	parameter off = 2 << 6;

	parameter loadi	= 	5'b00001;
	parameter loada =	loadi | abs;

	parameter store = 	5'b00010 | abs;

	parameter jump 	= 	5'b00100 | abs;
	parameter jumpz =	5'b00101 | abs;
	parameter jumpc =	5'b00110 | abs;
	parameter jumpn =	5'b00111 | abs;

	parameter add 	= 	6'b100000;
	parameter adc 	= 	6'b100001;
	parameter sbb 	= 	6'b100010;
	parameter sub 	= 	6'b100011;

	parameter adda 	= 	add | abs;
	parameter adca 	= 	adc | abs;
	parameter sbba 	= 	sbb | abs;
	parameter suba 	= 	sub | abs;
		
	parameter tmp = 10;
	parameter first = 11;
	parameter second = 12;
	parameter count = 13;

	integer org, start, finish;

	wire [WIDTH - 1:0] display;
	

	always @(posedge clk or posedge reset) begin
		if (reset == 1) begin
			start = 100;
			finish = 200;
			
			mem_addr_reg <= 0;

			for (i = 0; i < 2**(WIDTH - 1); i++)
				ram[i] = 0;
			
			org = start;

			ram[0] = org - 1;

			ram[first] = 0;
			ram[second] = 1;
			ram[count] = 7;

			start = org++;

			ram[start] = loada; ram[org++] = count;
			ram[org++] = sbb; ram[org++] = 0;
			ram[org++] = store; ram[org++] = count;

			ram[org++] = jumpz; ram[org++] = finish - 1;
			
			ram[org++] = loada; ram[org++] = second;
			ram[org++] = store; ram[org++] = tmp;

			ram[org++] = adda; ram[org++] = first;
			ram[org++] = store; ram[org++] = second;

			ram[org++] = loada; ram[org++] = tmp;
			ram[org++] = store; ram[org++] = first;
			
			ram[org++] = jump; ram[org++] = start - 1;

			ram[finish] = 8'hff;
		end else begin
			if (MI == 1)
				mem_addr_reg <= write;

			if (RI == 1)
				ram[mem_addr_reg] <= write;
		end
	end

	assign read = ram[mem_addr_reg];
	assign display = ram[first];
endmodule


module controlunit(clk, reset, inst, psr, cAI, cAS, cPI, cPS, cMI, cRI, cES, cCn, cL, cLS, cII, decode, counter);
	// Enable Control Lines

	parameter AI = 1 << 0;
	parameter AS = 1 << 1;
	parameter PI = 1 << 2;
	parameter PS = 1 << 3;
	parameter MI = 1 << 4;
	parameter RI = 1 << 5;
	parameter ES = 1 << 6;
	parameter Cn = 1 << 7;
	parameter LS = 1 << 8;
	parameter II = 1 << 9;

	// ALU Control Lines

	parameter GEN_0 = 14'b0000_0000000000 | LS;
	parameter GEN_1 = 14'b1111_0000000000 | LS;
	parameter BUF_A = 14'b1100_0000000000;
	parameter NEG_A = 14'b0011_0000000000;
	parameter BUF_B = 14'b1010_0000000000;
	parameter NEG_B = 14'b0101_0000000000;

	parameter load 	= 	6'b000001;
	parameter loadi = 	6'b000001;

	parameter store = 	6'b000010;

	parameter jump 	= 	6'b000100;
	parameter jumpz =	6'b000101;
	parameter jumpc =	6'b000110;
	parameter jumpn =	6'b000111;

	parameter add 	= 	6'b100000;
	parameter addc 	= 	6'b100001;
	parameter subb 	= 	6'b100010;
	parameter sub 	= 	6'b100011;
	
	parameter logic_nand = 	6'b010100;
	parameter logic_and = 	6'b010101;
	
	parameter logic_nor = 	6'b010110;
	parameter logic_or = 	6'b010111;
	
	parameter logic_xnor = 	6'b011000;
	parameter logic_xor = 	6'b011001;

	input clk;
	input reset;
	input [7:0] inst;
	input [3:0] psr;

	output wire cAI, cAS;
	output wire cPI, cPS;
	output wire cMI, cRI;
	output wire cES;
	output wire cCn;
	output wire cLS;
	output wire cII;
	output wire [3:0] cL;

	output [15:0] decode;
	output reg [2:0] counter;

	wire TYPE_REG, TYPE_IMM, TYPE_ABS, TYPE_OFF;
	wire [5:0] opcode;

	assign TYPE_IMM = ~inst[7] & ~inst[6];	// 0
	assign TYPE_ABS = ~inst[7] & inst[6];	// 1
	assign TYPE_OFF = inst[7] & ~inst[6];	// 2
	assign TYPE_REG = inst[7] & inst[6];	// 3

	assign opcode = inst[5:0];

	always @(negedge clk or posedge reset) begin
		if (reset == 1) begin
			counter <= 0;
		end else begin
			counter <= counter + 1;
		end
	end
	
	assign decode =
		counter == 0 ? GEN_0 | MI:
		counter == 1 ? BUF_B | Cn | MI | RI | LS:
		counter == 2 ? II | GEN_0 | MI:
		counter == 3 ? BUF_B | Cn | MI | RI | LS:
		counter == 4 ?
			TYPE_IMM ?
				opcode == load ? AI:

				opcode == add ? BUF_B | PI | AS | AI:
				opcode == addc ? BUF_B | PI | AS | AI | Cn:
				opcode == subb ? NEG_B | PI | AS | AI:
				opcode == sub ? NEG_B | PI | AS | AI | Cn:
				0:
			TYPE_ABS ?
				opcode == load ? BUF_B | MI | LS:

				opcode == store ? BUF_B | MI | LS:

				((opcode == jump) |
				((opcode == jumpz) & (psr[2] == 1)) |
				((opcode == jumpc) & (psr[0] == 1)) |
				((opcode == jumpn) & (psr[1] == 1))) ? GEN_0 | MI | AI:

				opcode == add ? BUF_B | MI | LS:
				opcode == addc ? BUF_B | MI | LS:
				opcode == sub ? BUF_B | MI | LS:
				opcode == subb ? BUF_B | MI | LS:
				0:
			0:
		counter == 5 ?
			TYPE_ABS ?
				opcode == load ? AI:

				opcode == store ? BUF_A | RI | LS:

				((opcode == jump) |
				((opcode == jumpz) & (psr[2] == 1)) |
				((opcode == jumpc) & (psr[0] == 1)) |
				((opcode == jumpn) & (psr[1] == 1))) ? BUF_A | MI | RI | LS:
				
				opcode == add ? BUF_B | PI | AS | AI:
				opcode == addc ? BUF_B | PI | AS | AI | Cn:
				opcode == subb ? NEG_B | PI | AS | AI:
				opcode == sub ? NEG_B | PI | AS | AI | Cn:
				0:
			0:
		0;
	
	always @(decode == 0) begin
		counter <= 0;
	end

	assign cAI = decode[0];
	assign cAS = decode[1];
	assign cPI = decode[2];
	assign cPS = decode[3];
	assign cMI = decode[4];
	assign cRI = decode[5];
	assign cES = decode[6];
	assign cCn = decode[7];
	assign cLS = decode[8];
	assign cII = decode[9];
	assign cL = decode[14:10];
endmodule

module processor #(parameter WIDTH = 16)(clk, reset, halt);
	wire [WIDTH - 1:0] mem_input_bus;
	wire [WIDTH - 1:0] accumulator_bus;
	wire [WIDTH - 1:0] ram_read_bus;
	wire [WIDTH - 1:0] ram_write_bus;
	wire [WIDTH - 1:0] alu_out_bus;
	wire [3:0] psr_bus;

	input clk;
	input reset;
	output reg halt;

	reg [7:0] inst;

	wire AI, AS;
	wire PI, PS;
	wire MI, RI;
	wire ES;
	wire C_in;
	wire LS;
	wire II;
	wire [3:0] L;

	alu16 #(WIDTH) alu (clk, reset, accumulator_bus, ram_read_bus, alu_out_bus, L, LS, C_in, PI, PS, psr_bus);

	// ES == 0 -> ALU
	// ES == 1 -> PSR
	assign ram_write_bus = ES ? psr_bus: alu_out_bus;

	sync_mux_2x1 #(WIDTH) rega_mux(clk, reset, AS, AI, ram_read_bus, ram_write_bus, accumulator_bus);

	wire [WIDTH - 1:0] mar;
	memory #(WIDTH) ram(clk, reset, MI, RI, ram_write_bus, ram_read_bus, mar);

	wire [15:0] decode;
	wire [2:0] counter;
	controlunit cu(clk, reset, inst, psr_bus, AI, AS, PI, PS, MI, RI, ES, C_in, L, LS, II, decode, counter);

	always @(posedge clk or posedge reset) begin
		if (reset == 1)
			inst <= 0;
		else if (II == 1) begin
			inst <= ram_read_bus;
			halt <= 0;
		end
	end

	always @(posedge clk & inst == 2**WIDTH - 1) begin
		halt <= 1;
	end
endmodule


module testbench;
	reg clk;
	reg reset;
	wire halt;

	processor #(8) tiny(clk, reset, halt);
	
	initial begin
		clk = 0;
		reset = 1;

		forever begin
			#1 clk = ~clk;
			if (reset == 1 & clk)
				reset = 0;
			else if (halt)
				$finish;
		end
	end

	initial begin
		$dumpfile ("testbench.vcd");
		$dumpvars (0, testbench);

		$monitor ($time, ":\tclk=%B | reset=%B | halt=%B", clk, reset, halt);

		#2000
		$finish;
	end
endmodule

testbench.vcd
$date
	Sun Dec 17 15:08:50 2023
$end
$version
	Icarus Verilog
$end
$timescale
	1s
$end
$scope module testbench $end
$var wire 1 ! halt $end
$var reg 1 " clk $end
$var reg 1 # reset $end
$scope module tiny $end
$var wire 1 " clk $end
$var wire 1 # reset $end
$var wire 8 $ ram_write_bus [7:0] $end
$var wire 8 % ram_read_bus [7:0] $end
$var wire 4 & psr_bus [3:0] $end
$var wire 8 ' mar [7:0] $end
$var wire 16 ( decode [15:0] $end
$var wire 3 ) counter [2:0] $end
$var wire 8 * alu_out_bus [7:0] $end
$var wire 8 + accumulator_bus [7:0] $end
$var wire 1 , RI $end
$var wire 1 - PS $end
$var wire 1 . PI $end
$var wire 1 / MI $end
$var wire 1 0 LS $end
$var wire 4 1 L [3:0] $end
$var wire 1 2 II $end
$var wire 1 3 ES $end
$var wire 1 4 C_in $end
$var wire 1 5 AS $end
$var wire 1 6 AI $end
$var parameter 32 7 WIDTH $end
$var reg 1 ! halt $end
$var reg 8 8 inst [7:0] $end
$scope module alu $end
$var wire 1 " clk $end
$var wire 1 # reset $end
$var wire 9 9 tE [8:0] $end
$var wire 8 : lB [7:0] $end
$var wire 8 ; lA [7:0] $end
$var wire 1 - PS $end
$var wire 1 . PI $end
$var wire 1 0 LS $end
$var wire 4 < L [3:0] $end
$var wire 8 = E [7:0] $end
$var wire 1 4 Cn $end
$var wire 8 > B [7:0] $end
$var wire 8 ? A [7:0] $end
$var parameter 32 @ WIDTH $end
$var reg 4 A psr [3:0] $end
$scope begin genblk1[0] $end
$var parameter 2 B i $end
$upscope $end
$scope begin genblk1[1] $end
$var parameter 2 C i $end
$upscope $end
$scope begin genblk1[2] $end
$var parameter 3 D i $end
$upscope $end
$scope begin genblk1[3] $end
$var parameter 3 E i $end
$upscope $end
$scope begin genblk1[4] $end
$var parameter 4 F i $end
$upscope $end
$scope begin genblk1[5] $end
$var parameter 4 G i $end
$upscope $end
$scope begin genblk1[6] $end
$var parameter 4 H i $end
$upscope $end
$scope begin genblk1[7] $end
$var parameter 4 I i $end
$upscope $end
$upscope $end
$scope module cu $end
$var wire 1 J TYPE_ABS $end
$var wire 1 K TYPE_IMM $end
$var wire 1 L TYPE_OFF $end
$var wire 1 M TYPE_REG $end
$var wire 1 " clk $end
$var wire 8 N inst [7:0] $end
$var wire 4 O psr [3:0] $end
$var wire 1 # reset $end
$var wire 6 P opcode [5:0] $end
$var wire 16 Q decode [15:0] $end
$var wire 1 , cRI $end
$var wire 1 - cPS $end
$var wire 1 . cPI $end
$var wire 1 / cMI $end
$var wire 1 0 cLS $end
$var wire 4 R cL [3:0] $end
$var wire 1 2 cII $end
$var wire 1 3 cES $end
$var wire 1 4 cCn $end
$var wire 1 5 cAS $end
$var wire 1 6 cAI $end
$var parameter 32 S AI $end
$var parameter 33 T AS $end
$var parameter 14 U BUF_A $end
$var parameter 14 V BUF_B $end
$var parameter 39 W Cn $end
$var parameter 38 X ES $end
$var parameter 40 Y GEN_0 $end
$var parameter 40 Z GEN_1 $end
$var parameter 41 [ II $end
$var parameter 40 \ LS $end
$var parameter 36 ] MI $end
$var parameter 14 ^ NEG_A $end
$var parameter 14 _ NEG_B $end
$var parameter 34 ` PI $end
$var parameter 35 a PS $end
$var parameter 37 b RI $end
$var parameter 6 c add $end
$var parameter 6 d addc $end
$var parameter 6 e jump $end
$var parameter 6 f jumpc $end
$var parameter 6 g jumpn $end
$var parameter 6 h jumpz $end
$var parameter 6 i load $end
$var parameter 6 j loadi $end
$var parameter 6 k logic_and $end
$var parameter 6 l logic_nand $end
$var parameter 6 m logic_nor $end
$var parameter 6 n logic_or $end
$var parameter 6 o logic_xnor $end
$var parameter 6 p logic_xor $end
$var parameter 6 q store $end
$var parameter 6 r sub $end
$var parameter 6 s subb $end
$var reg 3 t counter [2:0] $end
$upscope $end
$scope module ram $end
$var wire 1 / MI $end
$var wire 1 , RI $end
$var wire 1 " clk $end
$var wire 8 u display [7:0] $end
$var wire 8 v mar [7:0] $end
$var wire 8 w read [7:0] $end
$var wire 1 # reset $end
$var wire 8 x write [7:0] $end
$var parameter 32 y WIDTH $end
$var parameter 38 z abs $end
$var parameter 6 { adc $end
$var parameter 38 | adca $end
$var parameter 6 } add $end
$var parameter 38 ~ adda $end
$var parameter 32 !" count $end
$var parameter 32 "" first $end
$var parameter 38 #" imm $end
$var parameter 38 $" jump $end
$var parameter 38 %" jumpc $end
$var parameter 38 &" jumpn $end
$var parameter 38 '" jumpz $end
$var parameter 38 (" loada $end
$var parameter 5 )" loadi $end
$var parameter 38 *" off $end
$var parameter 6 +" sbb $end
$var parameter 38 ," sbba $end
$var parameter 32 -" second $end
$var parameter 38 ." store $end
$var parameter 6 /" sub $end
$var parameter 38 0" suba $end
$var parameter 32 1" tmp $end
$var reg 8 2" mem_addr_reg [7:0] $end
$var integer 32 3" finish [31:0] $end
$var integer 32 4" i [31:0] $end
$var integer 32 5" org [31:0] $end
$var integer 32 6" start [31:0] $end
$upscope $end
$scope module rega_mux $end
$var wire 1 " clk $end
$var wire 1 6 enable $end
$var wire 8 7" in0 [7:0] $end
$var wire 8 8" in1 [7:0] $end
$var wire 1 # reset $end
$var wire 1 5 sel $end
$var parameter 32 9" WIDTH $end
$var reg 8 :" out [7:0] $end
$upscope $end
$upscope $end
$upscope $end
$enddefinitions $end
$comment Show the parameter values. $end
$dumpall
b1000 9"
b1010 1"
b1100011 0"
b100011 /"
b1000010 ."
b1100 -"
b1100010 ,"
b100010 +"
b10000000 *"
b1 )"
b1000001 ("
b1000101 '"
b1000111 &"
b1000110 %"
b1000100 $"
b0 #"
b1011 ""
b1101 !"
b1100000 ~
b100000 }
b1100001 |
b100001 {
b1000000 z
b1000 y
b100010 s
b100011 r
b10 q
b11001 p
b11000 o
b10111 n
b10110 m
b10100 l
b10101 k
b1 j
b1 i
b101 h
b111 g
b110 f
b100 e
b100001 d
b100000 c
b100000 b
b1000 a
b100 `
b1010000000000 _
b110000000000 ^
b10000 ]
b100000000 \
b1000000000 [
b11110100000000 Z
b100000000 Y
b1000000 X
b10000000 W
b10100000000000 V
b11000000000000 U
b10 T
b1 S
b111 I
b110 H
b101 G
b100 F
b11 E
b10 D
b1 C
b0 B
b1000 @
b1000 7
$end
#0
$dumpvars
b0 :"
b0 8"
b1100011 7"
b1100100 6"
b1111010 5"
b10000000 4"
b11001000 3"
b0 2"
b0 x
b1100011 w
b0 v
b0 u
b0 t
b0 R
b100010000 Q
b0 P
bx O
b0 N
0M
0L
1K
0J
bx A
b0 ?
b1100011 >
b0 =
b0 <
b0 ;
b0 :
b0 9
b0 8
06
05
04
03
02
b0 1
10
1/
0.
0-
0,
b0 +
b0 *
b0 )
b100010000 (
b0 '
bx &
b1100011 %
b0 $
1#
0"
x!
$end
#1
0#
1"
#2
b1100011 :
b1100100 $
b1100100 x
b1100100 8"
b1100100 *
b1100100 =
b1100100 9
b1010 1
b1010 <
b1010 R
1,
14
b10100110110000 (
b10100110110000 Q
b1 )
b1 t
0"
#3
b1000010 $
b1000010 x
b1000010 8"
b1000010 *
b1000010 =
b1000010 9
b1000001 :
b1000001 %
b1000001 >
b1000001 w
b1000001 7"
b1100100 '
b1100100 v
b1100100 2"
1"
#4
b0 :
b0 $
b0 x
b0 8"
b0 *
b0 =
b0 9
b0 1
b0 <
b0 R
0,
04
12
b1100010000 (
b1100010000 Q
b10 )
b10 t
0"
#5
0K
1J
b1 P
0!
b1000001 8
b1000001 N
b1100100 %
b1100100 >
b1100100 w
b1100100 7"
b0 '
b0 v
b0 2"
1"
#6
b1100100 :
b1100101 $
b1100101 x
b1100101 8"
b1100101 *
b1100101 =
b1100101 9
b1010 1
b1010 <
b1010 R
1,
14
02
b10100110110000 (
b10100110110000 Q
b11 )
b11 t
0"
#7
b1110 $
b1110 x
b1110 8"
b1110 *
b1110 =
b1110 9
b1101 :
b1101 %
b1101 >
b1101 w
b1101 7"
b1100101 '
b1100101 v
b1100101 2"
1"
#8
b1101 $
b1101 x
b1101 8"
b1101 *
b1101 =
b1101 9
0,
04
b10100100010000 (
b10100100010000 Q
b100 )
b100 t
0"
#9
b111 $
b111 x
b111 8"
b111 *
b111 =
b111 9
b111 :
b111 %
b111 >
b111 w
b111 7"
b1101 '
b1101 v
b1101 2"
1"
#10
b0 $
b0 x
b0 8"
b0 *
b0 =
b0 9
b0 :
b0 1
b0 <
b0 R
16
0/
00
b1 (
b1 Q
b101 )
b101 t
0"
#11
b111 $
b111 x
b111 8"
b111 *
b111 =
b111 9
b111 ;
b111 +
b111 ?
b111 :"
1"
#12
b0 $
b0 x
b0 8"
b0 *
b0 =
b0 9
b0 ;
1/
10
06
b100010000 (
b100010000 Q
b0 )
b0 t
0"
#13
b1100101 %
b1100101 >
b1100101 w
b1100101 7"
b0 '
b0 v
b0 2"
1"
#14
b1100101 :
b1100110 $
b1100110 x
b1100110 8"
b1100110 *
b1100110 =
b1100110 9
b1010 1
b1010 <
b1010 R
1,
14
b10100110110000 (
b10100110110000 Q
b1 )
b1 t
0"
#15
b100011 $
b100011 x
b100011 8"
b100011 *
b100011 =
b100011 9
b100010 :
b100010 %
b100010 >
b100010 w
b100010 7"
b1100110 '
b1100110 v
b1100110 2"
1"
#16
b0 :
b0 $
b0 x
b0 8"
b0 *
b0 =
b0 9
b0 1
b0 <
b0 R
0,
04
12
b1100010000 (
b1100010000 Q
b10 )
b10 t
0"
#17
1K
0J
b100010 P
b100010 8
b100010 N
b1100110 %
b1100110 >
b1100110 w
b1100110 7"
b0 '
b0 v
b0 2"
1"
#18
b1100110 :
b1100111 $
b1100111 x
b1100111 8"
b1100111 *
b1100111 =
b1100111 9
b1010 1
b1010 <
b1010 R
1,
14
02
b10100110110000 (
b10100110110000 Q
b11 )
b11 t
0"
#19
b1 $
b1 x
b1 8"
b1 *
b1 =
b1 9
b0 :
b0 %
b0 >
b0 w
b0 7"
b1100111 '
b1100111 v
b1100111 2"
1"
#20
b11111111 :
b110 $
b110 x
b110 8"
b110 *
b110 =
b100000110 9
b111 ;
b101 1
b101 <
b101 R
16
15
1.
0/
0,
04
00
b1010000000111 (
b1010000000111 Q
b100 )
b100 t
0"
#21
b1 &
b1 A
b1 O
b101 $
b101 x
b101 8"
b101 *
b101 =
b100000101 9
b110 ;
b110 +
b110 ?
b110 :"
1"
#22
b0 ;
1/
10
b0 $
b0 x
b0 8"
b0 *
b0 =
b0 9
b0 :
b0 1
b0 <
b0 R
06
05
0.
b100010000 (
b100010000 Q
b0 )
b0 t
0"
#23
b1100111 %
b1100111 >
b1100111 w
b1100111 7"
b0 '
b0 v
b0 2"
1"
#24
b1100111 :
b1101000 $
b1101000 x
b1101000 8"
b1101000 *
b1101000 =
b1101000 9
b1010 1
b1010 <
b1010 R
1,
14
b10100110110000 (
b10100110110000 Q
b1 )
b1 t
0"
#25
b1000011 $
b1000011 x
b1000011 8"
b1000011 *
b1000011 =
b1000011 9
b1000010 :
b1000010 %
b1000010 >
b1000010 w
b1000010 7"
b1101000 '
b1101000 v
b1101000 2"
1"
#26
b0 :
b0 $
b0 x
b0 8"
b0 *
b0 =
b0 9
b0 1
b0 <
b0 R
0,
04
12
b1100010000 (
b1100010000 Q
b10 )
b10 t
0"
#27
0K
1J
b10 P
b1101000 %
b1101000 >
b1101000 w
b1101000 7"
b0 '
b0 v
b0 2"
b1000010 8
b1000010 N
1"
#28
b1101000 :
b1101001 $
b1101001 x
b1101001 8"
b1101001 *
b1101001 =
b1101001 9
b1010 1
b1010 <
b1010 R
1,
14
02
b10100110110000 (
b10100110110000 Q
b11 )
b11 t
0"
#29
b1110 $
b1110 x
b1110 8"
b1110 *
b1110 =
b1110 9
b1101 :
b1101 %
b1101 >
b1101 w
b1101 7"
b1101001 '
b1101001 v
b1101001 2"
1"
#30
b1101 $
b1101 x
b1101 8"
b1101 *
b1101 =
b1101 9
0,
04
b10100100010000 (
b10100100010000 Q
b100 )
b100 t
0"
#31
b111 $
b111 x
b111 8"
b111 *
b111 =
b111 9
b111 :
b111 %
b111 >
b111 w
b111 7"
b1101 '
b1101 v
b1101 2"
1"
#32
b110 $
b110 x
b110 8"
b110 *
b110 =
b110 9
b110 :
b1100 1
b1100 <
b1100 R
0/
1,
b11000100100000 (
b11000100100000 Q
b101 )
b101 t
0"
#33
b110 %
b110 >
b110 w
b110 7"
1"
#34
1/
b0 :
b0 $
b0 x
b0 8"
b0 *
b0 =
b0 9
b0 ;
b0 1
b0 <
b0 R
0,
10
b100010000 (
b100010000 Q
b0 )
b0 t
0"
#35
b1101001 %
b1101001 >
b1101001 w
b1101001 7"
b0 '
b0 v
b0 2"
1"
#36
b1101001 :
b1101010 $
b1101010 x
b1101010 8"
b1101010 *
b1101010 =
b1101010 9
b1010 1
b1010 <
b1010 R
1,
14
b10100110110000 (
b10100110110000 Q
b1 )
b1 t
0"
#37
b1000110 $
b1000110 x
b1000110 8"
b1000110 *
b1000110 =
b1000110 9
b1000101 :
b1000101 %
b1000101 >
b1000101 w
b1000101 7"
b1101010 '
b1101010 v
b1101010 2"
1"
#38
b0 :
b0 $
b0 x
b0 8"
b0 *
b0 =
b0 9
b0 1
b0 <
b0 R
0,
04
12
b1100010000 (
b1100010000 Q
b10 )
b10 t
0"
#39
b101 P
b1101010 %
b1101010 >
b1101010 w
b1101010 7"
b0 '
b0 v
b0 2"
b1000101 8
b1000101 N
1"
#40
b1101010 :
b1101011 $
b1101011 x
b1101011 8"
b1101011 *
b1101011 =
b1101011 9
b1010 1
b1010 <
b1010 R
1,
14
02
b10100110110000 (
b10100110110000 Q
b11 )
b11 t
0"
#41
b11001000 $
b11001000 x
b11001000 8"
b11001000 *
b11001000 =
b11001000 9
b11000111 :
b11000111 %
b11000111 >
b11000111 w
b11000111 7"
b1101011 '
b1101011 v
b1101011 2"
1"
#42
b0 :
b0 $
b0 x
b0 8"
b0 *
b0 =
b0 9
b0 ;
b0 1
b0 <
b0 R
1/
0,
04
10
b100010000 (
b100010000 Q
b0 )
b0 t
0"
#43
b1101011 %
b1101011 >
b1101011 w
b1101011 7"
b0 '
b0 v
b0 2"
1"
#44
b1101011 :
b1101100 $
b1101100 x
b1101100 8"
b1101100 *
b1101100 =
b1101100 9
b1010 1
b1010 <
b1010 R
1,
14
b10100110110000 (
b10100110110000 Q
b1 )
b1 t
0"
#45
b1000010 $
b1000010 x
b1000010 8"
b1000010 *
b1000010 =
b1000010 9
b1000001 :
b1000001 %
b1000001 >
b1000001 w
b1000001 7"
b1101100 '
b1101100 v
b1101100 2"
1"
#46
b0 :
b0 $
b0 x
b0 8"
b0 *
b0 =
b0 9
b0 1
b0 <
b0 R
0,
04
12
b1100010000 (
b1100010000 Q
b10 )
b10 t
0"
#47
b1 P
b1101100 %
b1101100 >
b1101100 w
b1101100 7"
b0 '
b0 v
b0 2"
b1000001 8
b1000001 N
1"
#48
b1101100 :
b1101101 $
b1101101 x
b1101101 8"
b1101101 *
b1101101 =
b1101101 9
b1010 1
b1010 <
b1010 R
1,
14
02
b10100110110000 (
b10100110110000 Q
b11 )
b11 t
0"
#49
b1101 $
b1101 x
b1101 8"
b1101 *
b1101 =
b1101 9
b1100 :
b1100 %
b1100 >
b1100 w
b1100 7"
b1101101 '
b1101101 v
b1101101 2"
1"
#50
b1100 $
b1100 x
b1100 8"
b1100 *
b1100 =
b1100 9
0,
04
b10100100010000 (
b10100100010000 Q
b100 )
b100 t
0"
#51
b1 $
b1 x
b1 8"
b1 *
b1 =
b1 9
b1 :
b1 %
b1 >
b1 w
b1 7"
b1100 '
b1100 v
b1100 2"
1"
#52
b0 :
b110 $
b110 x
b110 8"
b110 *
b110 =
b110 9
b110 ;
b0 1
b0 <
b0 R
16
0/
00
b1 (
b1 Q
b101 )
b101 t
0"
#53
b1 $
b1 x
b1 8"
b1 *
b1 =
b1 9
b1 ;
b1 +
b1 ?
b1 :"
1"
#54
b0 $
b0 x
b0 8"
b0 *
b0 =
b0 9
b0 ;
1/
10
06
b100010000 (
b100010000 Q
b0 )
b0 t
0"
#55
b1101101 %
b1101101 >
b1101101 w
b1101101 7"
b0 '
b0 v
b0 2"
1"
#56
b1101101 :
b1101110 $
b1101110 x
b1101110 8"
b1101110 *
b1101110 =
b1101110 9
b1010 1
b1010 <
b1010 R
1,
14
b10100110110000 (
b10100110110000 Q
b1 )
b1 t
0"
#57
b1000011 $
b1000011 x
b1000011 8"
b1000011 *
b1000011 =
b1000011 9
b1000010 :
b1000010 %
b1000010 >
b1000010 w
b1000010 7"
b1101110 '
b1101110 v
b1101110 2"
1"
#58
b0 :
b0 $
b0 x
b0 8"
b0 *
b0 =
b0 9
b0 1
b0 <
b0 R
0,
04
12
b1100010000 (
b1100010000 Q
b10 )
b10 t
0"
#59
b10 P
b1101110 %
b1101110 >
b1101110 w
b1101110 7"
b0 '
b0 v
b0 2"
b1000010 8
b1000010 N
1"
#60
b1101110 :
b1101111 $
b1101111 x
b1101111 8"
b1101111 *
b1101111 =
b1101111 9
b1010 1
b1010 <
b1010 R
1,
14
02
b10100110110000 (
b10100110110000 Q
b11 )
b11 t
0"
#61
b1011 $
b1011 x
b1011 8"
b1011 *
b1011 =
b1011 9
b1010 :
b1010 %
b1010 >
b1010 w
b1010 7"
b1101111 '
b1101111 v
b1101111 2"
1"
#62
b1010 $
b1010 x
b1010 8"
b1010 *
b1010 =
b1010 9
0,
04
b10100100010000 (
b10100100010000 Q
b100 )
b100 t
0"
#63
b0 $
b0 x
b0 8"
b0 *
b0 =
b0 9
b0 :
b0 %
b0 >
b0 w
b0 7"
b1010 '
b1010 v
b1010 2"
1"
#64
b1 $
b1 x
b1 8"
b1 *
b1 =
b1 9
b1 :
b1100 1
b1100 <
b1100 R
0/
1,
b11000100100000 (
b11000100100000 Q
b101 )
b101 t
0"
#65
b1 %
b1 >
b1 w
b1 7"
1"
#66
1/
b0 :
b0 $
b0 x
b0 8"
b0 *
b0 =
b0 9
b0 ;
b0 1
b0 <
b0 R
0,
10
b100010000 (
b100010000 Q
b0 )
b0 t
0"
#67
b1101111 %
b1101111 >
b1101111 w
b1101111 7"
b0 '
b0 v
b0 2"
1"
#68
b1101111 :
b1110000 $
b1110000 x
b1110000 8"
b1110000 *
b1110000 =
b1110000 9
b1010 1
b1010 <
b1010 R
1,
14
b10100110110000 (
b10100110110000 Q
b1 )
b1 t
0"
#69
b1100001 $
b1100001 x
b1100001 8"
b1100001 *
b1100001 =
b1100001 9
b1100000 :
b1100000 %
b1100000 >
b1100000 w
b1100000 7"
b1110000 '
b1110000 v
b1110000 2"
1"
#70
b0 :
b0 $
b0 x
b0 8"
b0 *
b0 =
b0 9
b0 1
b0 <
b0 R
0,
04
12
b1100010000 (
b1100010000 Q
b10 )
b10 t
0"
#71
b100000 P
b1110000 %
b1110000 >
b1110000 w
b1110000 7"
b0 '
b0 v
b0 2"
b1100000 8
b1100000 N
1"
#72
b1110000 :
b1110001 $
b1110001 x
b1110001 8"
b1110001 *
b1110001 =
b1110001 9
b1010 1
b1010 <
b1010 R
1,
14
02
b10100110110000 (
b10100110110000 Q
b11 )
b11 t
0"
#73
b1100 $
b1100 x
b1100 8"
b1100 *
b1100 =
b1100 9
b1011 :
b1011 %
b1011 >
b1011 w
b1011 7"
b1110001 '
b1110001 v
b1110001 2"
1"
#74
b1011 $
b1011 x
b1011 8"
b1011 *
b1011 =
b1011 9
0,
04
b10100100010000 (
b10100100010000 Q
b100 )
b100 t
0"
#75
b0 $
b0 x
b0 8"
b0 *
b0 =
b0 9
b0 :
b0 %
b0 >
b0 w
b0 7"
b1011 '
b1011 v
b1011 2"
1"
#76
b1 $
b1 x
b1 8"
b1 *
b1 =
b1 9
b1 ;
16
15
1.
0/
00
b10100000000111 (
b10100000000111 Q
b101 )
b101 t
0"
#77
b0 &
b0 A
b0 O
1"
